{"pagination":{"last_visible_page":3,"has_next_page":true,"current_page":2,"items":{"count":25,"total":56,"per_page":25}},"data":[{"mal_id":50923,"url":"https:\/\/myanimelist.net\/anime\/50923\/Mushikaburi-hime","images":{"jpg":{"image_url":"https:\/\/cdn.myanimelist.net\/images\/anime\/1256\/128714.jpg","small_image_url":"https:\/\/cdn.myanimelist.net\/images\/anime\/1256\/128714t.jpg","large_image_url":"https:\/\/cdn.myanimelist.net\/images\/anime\/1256\/128714l.jpg"},"webp":{"image_url":"https:\/\/cdn.myanimelist.net\/images\/anime\/1256\/128714.webp","small_image_url":"https:\/\/cdn.myanimelist.net\/images\/anime\/1256\/128714t.webp","large_image_url":"https:\/\/cdn.myanimelist.net\/images\/anime\/1256\/128714l.webp"}},"trailer":{"youtube_id":"W2llbRzsic8","url":"https:\/\/www.youtube.com\/watch?v=W2llbRzsic8","embed_url":"https:\/\/www.youtube.com\/embed\/W2llbRzsic8?enablejsapi=1&wmode=opaque&autoplay=1","images":{"image_url":"https:\/\/img.youtube.com\/vi\/W2llbRzsic8\/default.jpg","small_image_url":"https:\/\/img.youtube.com\/vi\/W2llbRzsic8\/sddefault.jpg","medium_image_url":"https:\/\/img.youtube.com\/vi\/W2llbRzsic8\/mqdefault.jpg","large_image_url":"https:\/\/img.youtube.com\/vi\/W2llbRzsic8\/hqdefault.jpg","maximum_image_url":"https:\/\/img.youtube.com\/vi\/W2llbRzsic8\/maxresdefault.jpg"}},"approved":true,"titles":[{"type":"Default","title":"Mushikaburi-hime"},{"type":"Synonym","title":"Princess of the Bibliophile"},{"type":"Japanese","title":"\u866b\u304b\u3076\u308a\u59eb"},{"type":"English","title":"Bibliophile Princess"}],"title":"Mushikaburi-hime","title_english":"Bibliophile Princess","title_japanese":"\u866b\u304b\u3076\u308a\u59eb","title_synonyms":["Princess of the Bibliophile"],"type":"TV","source":"Light novel","episodes":12,"status":"Currently Airing","airing":true,"aired":{"from":"2022-10-06T00:00:00+00:00","to":null,"prop":{"from":{"day":6,"month":10,"year":2022},"to":{"day":null,"month":null,"year":null}},"string":"Oct 6, 2022 to ?"},"duration":"23 min per ep","rating":"PG-13 - Teens 13 or older","score":7.24,"scored_by":4104,"rank":2792,"popularity":3275,"members":36243,"favorites":217,"synopsis":"For as long as she could read, Elianna Bernstein\u2014more commonly known as the \"Bibliophile Princess\"\u2014has preferred the company of books to that of people. However, as a noble, it is her duty to find a suitor. Fortunately for her, Crown Prince Christopher Selkirk Asherald proposes a deal: He will protect her free time, and, in exchange, Elianna will be his fianc\u00e9e in name only. The years they spend together are bliss, as Elianna learns to open herself to others. But all good things must come to an end. For Elianna, who loves books more than people, ending their fake relationship should be no big deal. But as Christopher grows close with another girl, Elianna begins to realize that she is not as indifferent to him as she once thought. [Written by MAL Rewrite]","background":null,"season":"fall","year":2022,"broadcast":{"day":"Thursdays","time":"21:00","timezone":"Asia\/Tokyo","string":"Thursdays at 21:00 (JST)"},"producers":[{"mal_id":238,"type":"anime","name":"AT-X","url":"https:\/\/myanimelist.net\/anime\/producer\/238\/AT-X"},{"mal_id":1211,"type":"anime","name":"Tokyo MX","url":"https:\/\/myanimelist.net\/anime\/producer\/1211\/Tokyo_MX"},{"mal_id":1412,"type":"anime","name":"Kansai Telecasting","url":"https:\/\/myanimelist.net\/anime\/producer\/1412\/Kansai_Telecasting"},{"mal_id":1582,"type":"anime","name":"Ichijinsha","url":"https:\/\/myanimelist.net\/anime\/producer\/1582\/Ichijinsha"},{"mal_id":1680,"type":"anime","name":"BS NTV","url":"https:\/\/myanimelist.net\/anime\/producer\/1680\/BS_NTV"},{"mal_id":1696,"type":"anime","name":"Kadokawa","url":"https:\/\/myanimelist.net\/anime\/producer\/1696\/Kadokawa"}],"licensors":[{"mal_id":376,"type":"anime","name":"Sentai Filmworks","url":"https:\/\/myanimelist.net\/anime\/producer\/376\/Sentai_Filmworks"}],"studios":[{"mal_id":11,"type":"anime","name":"Madhouse","url":"https:\/\/myanimelist.net\/anime\/producer\/11\/Madhouse"}],"genres":[{"mal_id":8,"type":"anime","name":"Drama","url":"https:\/\/myanimelist.net\/anime\/genre\/8\/Drama"},{"mal_id":22,"type":"anime","name":"Romance","url":"https:\/\/myanimelist.net\/anime\/genre\/22\/Romance"}],"explicit_genres":[],"themes":[{"mal_id":13,"type":"anime","name":"Historical","url":"https:\/\/myanimelist.net\/anime\/genre\/13\/Historical"}],"demographics":[]},{"mal_id":51212,"url":"https:\/\/myanimelist.net\/anime\/51212\/Futoku_no_Guild","images":{"jpg":{"image_url":"https:\/\/cdn.myanimelist.net\/images\/anime\/1651\/128718.jpg","small_image_url":"https:\/\/cdn.myanimelist.net\/images\/anime\/1651\/128718t.jpg","large_image_url":"https:\/\/cdn.myanimelist.net\/images\/anime\/1651\/128718l.jpg"},"webp":{"image_url":"https:\/\/cdn.myanimelist.net\/images\/anime\/1651\/128718.webp","small_image_url":"https:\/\/cdn.myanimelist.net\/images\/anime\/1651\/128718t.webp","large_image_url":"https:\/\/cdn.myanimelist.net\/images\/anime\/1651\/128718l.webp"}},"trailer":{"youtube_id":"MrKZYoV4NSo","url":"https:\/\/www.youtube.com\/watch?v=MrKZYoV4NSo","embed_url":"https:\/\/www.youtube.com\/embed\/MrKZYoV4NSo?enablejsapi=1&wmode=opaque&autoplay=1","images":{"image_url":"https:\/\/img.youtube.com\/vi\/MrKZYoV4NSo\/default.jpg","small_image_url":"https:\/\/img.youtube.com\/vi\/MrKZYoV4NSo\/sddefault.jpg","medium_image_url":"https:\/\/img.youtube.com\/vi\/MrKZYoV4NSo\/mqdefault.jpg","large_image_url":"https:\/\/img.youtube.com\/vi\/MrKZYoV4NSo\/hqdefault.jpg","maximum_image_url":"https:\/\/img.youtube.com\/vi\/MrKZYoV4NSo\/maxresdefault.jpg"}},"approved":true,"titles":[{"type":"Default","title":"Futoku no Guild"},{"type":"Synonym","title":"Guild of Depravity"},{"type":"Japanese","title":"\u4e0d\u5fb3\u306e\u30ae\u30eb\u30c9"},{"type":"English","title":"Immoral Guild"}],"title":"Futoku no Guild","title_english":"Immoral Guild","title_japanese":"\u4e0d\u5fb3\u306e\u30ae\u30eb\u30c9","title_synonyms":["Guild of Depravity"],"type":"TV","source":"Manga","episodes":12,"status":"Currently Airing","airing":true,"aired":{"from":"2022-10-05T00:00:00+00:00","to":null,"prop":{"from":{"day":5,"month":10,"year":2022},"to":{"day":null,"month":null,"year":null}},"string":"Oct 5, 2022 to ?"},"duration":"24 min per ep","rating":"R+ - Mild Nudity","score":6.18,"scored_by":4849,"rank":8222,"popularity":3281,"members":36130,"favorites":123,"synopsis":"Kikuru Madan, is a monster hunter with excellent performance, because of his particular job in the forest, but he decided to quit it because of fear wasting his own youth... (Source: LHTranslation)","background":null,"season":"fall","year":2022,"broadcast":{"day":"Wednesdays","time":"23:30","timezone":"Asia\/Tokyo","string":"Wednesdays at 23:30 (JST)"},"producers":[{"mal_id":58,"type":"anime","name":"Square Enix","url":"https:\/\/myanimelist.net\/anime\/producer\/58\/Square_Enix"},{"mal_id":104,"type":"anime","name":"Lantis","url":"https:\/\/myanimelist.net\/anime\/producer\/104\/Lantis"},{"mal_id":238,"type":"anime","name":"AT-X","url":"https:\/\/myanimelist.net\/anime\/producer\/238\/AT-X"},{"mal_id":1444,"type":"anime","name":"Egg Firm","url":"https:\/\/myanimelist.net\/anime\/producer\/1444\/Egg_Firm"},{"mal_id":1696,"type":"anime","name":"Kadokawa","url":"https:\/\/myanimelist.net\/anime\/producer\/1696\/Kadokawa"},{"mal_id":2425,"type":"anime","name":"Bandai Namco Music Live","url":"https:\/\/myanimelist.net\/anime\/producer\/2425\/Bandai_Namco_Music_Live"}],"licensors":[],"studios":[{"mal_id":120,"type":"anime","name":"TNK","url":"https:\/\/myanimelist.net\/anime\/producer\/120\/TNK"}],"genres":[{"mal_id":4,"type":"anime","name":"Comedy","url":"https:\/\/myanimelist.net\/anime\/genre\/4\/Comedy"},{"mal_id":10,"type":"anime","name":"Fantasy","url":"https:\/\/myanimelist.net\/anime\/genre\/10\/Fantasy"},{"mal_id":9,"type":"anime","name":"Ecchi","url":"https:\/\/myanimelist.net\/anime\/genre\/9\/Ecchi"}],"explicit_genres":[],"themes":[{"mal_id":35,"type":"anime","name":"Harem","url":"https:\/\/myanimelist.net\/anime\/genre\/35\/Harem"}],"demographics":[{"mal_id":27,"type":"anime","name":"Shounen","url":"https:\/\/myanimelist.net\/anime\/genre\/27\/Shounen"}]},{"mal_id":50348,"url":"https:\/\/myanimelist.net\/anime\/50348\/Peter_Grill_to_Kenja_no_Jikan__Super_Extra","images":{"jpg":{"image_url":"https:\/\/cdn.myanimelist.net\/images\/anime\/1702\/128716.jpg","small_image_url":"https:\/\/cdn.myanimelist.net\/images\/anime\/1702\/128716t.jpg","large_image_url":"https:\/\/cdn.myanimelist.net\/images\/anime\/1702\/128716l.jpg"},"webp":{"image_url":"https:\/\/cdn.myanimelist.net\/images\/anime\/1702\/128716.webp","small_image_url":"https:\/\/cdn.myanimelist.net\/images\/anime\/1702\/128716t.webp","large_image_url":"https:\/\/cdn.myanimelist.net\/images\/anime\/1702\/128716l.webp"}},"trailer":{"youtube_id":"txIZFXwTrtY","url":"https:\/\/www.youtube.com\/watch?v=txIZFXwTrtY","embed_url":"https:\/\/www.youtube.com\/embed\/txIZFXwTrtY?enablejsapi=1&wmode=opaque&autoplay=1","images":{"image_url":"https:\/\/img.youtube.com\/vi\/txIZFXwTrtY\/default.jpg","small_image_url":"https:\/\/img.youtube.com\/vi\/txIZFXwTrtY\/sddefault.jpg","medium_image_url":"https:\/\/img.youtube.com\/vi\/txIZFXwTrtY\/mqdefault.jpg","large_image_url":"https:\/\/img.youtube.com\/vi\/txIZFXwTrtY\/hqdefault.jpg","maximum_image_url":"https:\/\/img.youtube.com\/vi\/txIZFXwTrtY\/maxresdefault.jpg"}},"approved":true,"titles":[{"type":"Default","title":"Peter Grill to Kenja no Jikan: Super Extra"},{"type":"Synonym","title":"Peter Grill to Kenja no Jikan 2nd Season"},{"type":"Japanese","title":"\u30d4\u30fc\u30bf\u30fc\u30fb\u30b0\u30ea\u30eb\u3068\u8ce2\u8005\u306e\u6642\u9593 Super Extra"},{"type":"English","title":"Peter Grill and the Philosopher's Time: Super Extra"}],"title":"Peter Grill to Kenja no Jikan: Super Extra","title_english":"Peter Grill and the Philosopher's Time: Super Extra","title_japanese":"\u30d4\u30fc\u30bf\u30fc\u30fb\u30b0\u30ea\u30eb\u3068\u8ce2\u8005\u306e\u6642\u9593 Super Extra","title_synonyms":["Peter Grill to Kenja no Jikan 2nd Season"],"type":"TV","source":"Manga","episodes":12,"status":"Currently Airing","airing":true,"aired":{"from":"2022-10-10T00:00:00+00:00","to":null,"prop":{"from":{"day":10,"month":10,"year":2022},"to":{"day":null,"month":null,"year":null}},"string":"Oct 10, 2022 to ?"},"duration":"12 min per ep","rating":"R+ - Mild Nudity","score":6.43,"scored_by":2700,"rank":6796,"popularity":3448,"members":32683,"favorites":108,"synopsis":"Second season of Peter Grill to Kenja no Jikan.","background":null,"season":"fall","year":2022,"broadcast":{"day":"Mondays","time":"01:15","timezone":"Asia\/Tokyo","string":"Mondays at 01:15 (JST)"},"producers":[{"mal_id":517,"type":"anime","name":"Asmik Ace","url":"https:\/\/myanimelist.net\/anime\/producer\/517\/Asmik_Ace"},{"mal_id":843,"type":"anime","name":"BS Fuji","url":"https:\/\/myanimelist.net\/anime\/producer\/843\/BS_Fuji"},{"mal_id":1377,"type":"anime","name":"Futabasha","url":"https:\/\/myanimelist.net\/anime\/producer\/1377\/Futabasha"},{"mal_id":1397,"type":"anime","name":"Universal Music Japan","url":"https:\/\/myanimelist.net\/anime\/producer\/1397\/Universal_Music_Japan"},{"mal_id":2233,"type":"anime","name":"Starry Cube","url":"https:\/\/myanimelist.net\/anime\/producer\/2233\/Starry_Cube"},{"mal_id":2236,"type":"anime","name":"CTW","url":"https:\/\/myanimelist.net\/anime\/producer\/2236\/CTW"},{"mal_id":2237,"type":"anime","name":"FUTURE LEAP","url":"https:\/\/myanimelist.net\/anime\/producer\/2237\/FUTURE_LEAP_"}],"licensors":[{"mal_id":376,"type":"anime","name":"Sentai Filmworks","url":"https:\/\/myanimelist.net\/anime\/producer\/376\/Sentai_Filmworks"}],"studios":[{"mal_id":541,"type":"anime","name":"Seven","url":"https:\/\/myanimelist.net\/anime\/producer\/541\/Seven"},{"mal_id":2052,"type":"anime","name":"Wolfsbane","url":"https:\/\/myanimelist.net\/anime\/producer\/2052\/Wolfsbane"}],"genres":[{"mal_id":4,"type":"anime","name":"Comedy","url":"https:\/\/myanimelist.net\/anime\/genre\/4\/Comedy"},{"mal_id":10,"type":"anime","name":"Fantasy","url":"https:\/\/myanimelist.net\/anime\/genre\/10\/Fantasy"},{"mal_id":9,"type":"anime","name":"Ecchi","url":"https:\/\/myanimelist.net\/anime\/genre\/9\/Ecchi"}],"explicit_genres":[],"themes":[{"mal_id":35,"type":"anime","name":"Harem","url":"https:\/\/myanimelist.net\/anime\/genre\/35\/Harem"}],"demographics":[]},{"mal_id":49849,"url":"https:\/\/myanimelist.net\/anime\/49849\/Shinmai_Renkinjutsushi_no_Tenpo_Keiei","images":{"jpg":{"image_url":"https:\/\/cdn.myanimelist.net\/images\/anime\/1993\/125560.jpg","small_image_url":"https:\/\/cdn.myanimelist.net\/images\/anime\/1993\/125560t.jpg","large_image_url":"https:\/\/cdn.myanimelist.net\/images\/anime\/1993\/125560l.jpg"},"webp":{"image_url":"https:\/\/cdn.myanimelist.net\/images\/anime\/1993\/125560.webp","small_image_url":"https:\/\/cdn.myanimelist.net\/images\/anime\/1993\/125560t.webp","large_image_url":"https:\/\/cdn.myanimelist.net\/images\/anime\/1993\/125560l.webp"}},"trailer":{"youtube_id":"q7iWCME2HLY","url":"https:\/\/www.youtube.com\/watch?v=q7iWCME2HLY","embed_url":"https:\/\/www.youtube.com\/embed\/q7iWCME2HLY?enablejsapi=1&wmode=opaque&autoplay=1","images":{"image_url":"https:\/\/img.youtube.com\/vi\/q7iWCME2HLY\/default.jpg","small_image_url":"https:\/\/img.youtube.com\/vi\/q7iWCME2HLY\/sddefault.jpg","medium_image_url":"https:\/\/img.youtube.com\/vi\/q7iWCME2HLY\/mqdefault.jpg","large_image_url":"https:\/\/img.youtube.com\/vi\/q7iWCME2HLY\/hqdefault.jpg","maximum_image_url":"https:\/\/img.youtube.com\/vi\/q7iWCME2HLY\/maxresdefault.jpg"}},"approved":true,"titles":[{"type":"Default","title":"Shinmai Renkinjutsushi no Tenpo Keiei"},{"type":"Japanese","title":"\u65b0\u7c73\u932c\u91d1\u8853\u5e2b\u306e\u5e97\u8217\u7d4c\u55b6"},{"type":"English","title":"Management of a Novice Alchemist"}],"title":"Shinmai Renkinjutsushi no Tenpo Keiei","title_english":"Management of a Novice Alchemist","title_japanese":"\u65b0\u7c73\u932c\u91d1\u8853\u5e2b\u306e\u5e97\u8217\u7d4c\u55b6","title_synonyms":[],"type":"TV","source":"Light novel","episodes":12,"status":"Currently Airing","airing":true,"aired":{"from":"2022-10-03T00:00:00+00:00","to":null,"prop":{"from":{"day":3,"month":10,"year":2022},"to":{"day":null,"month":null,"year":null}},"string":"Oct 3, 2022 to ?"},"duration":"23 min per ep","rating":"PG-13 - Teens 13 or older","score":6.71,"scored_by":4437,"rank":5300,"popularity":3578,"members":30380,"favorites":85,"synopsis":"Shoot for the stars! I'm going to be the country's number one alchemist! When young girl Sarasa graduated from the Royal Alchemist Academy, her teacher gifted her a house for her to set up shop. Aiming to become a masterclass alchemist, she gathers materials herself, experiments and operates a business. In her very own atelier, Sarasa indulges in a slow and relaxed alchemist life! (Source: Kadokawa, edited)","background":null,"season":"fall","year":2022,"broadcast":{"day":"Mondays","time":"21:00","timezone":"Asia\/Tokyo","string":"Mondays at 21:00 (JST)"},"producers":[{"mal_id":238,"type":"anime","name":"AT-X","url":"https:\/\/myanimelist.net\/anime\/producer\/238\/AT-X"},{"mal_id":323,"type":"anime","name":"Nippon Columbia","url":"https:\/\/myanimelist.net\/anime\/producer\/323\/Nippon_Columbia"},{"mal_id":1345,"type":"anime","name":"Sammy","url":"https:\/\/myanimelist.net\/anime\/producer\/1345\/Sammy"},{"mal_id":1696,"type":"anime","name":"Kadokawa","url":"https:\/\/myanimelist.net\/anime\/producer\/1696\/Kadokawa"},{"mal_id":2607,"type":"anime","name":"Kill Time Communication","url":"https:\/\/myanimelist.net\/anime\/producer\/2607\/Kill_Time_Communication"}],"licensors":[{"mal_id":376,"type":"anime","name":"Sentai Filmworks","url":"https:\/\/myanimelist.net\/anime\/producer\/376\/Sentai_Filmworks"}],"studios":[{"mal_id":1974,"type":"anime","name":"ENGI","url":"https:\/\/myanimelist.net\/anime\/producer\/1974\/ENGI"}],"genres":[{"mal_id":2,"type":"anime","name":"Adventure","url":"https:\/\/myanimelist.net\/anime\/genre\/2\/Adventure"},{"mal_id":10,"type":"anime","name":"Fantasy","url":"https:\/\/myanimelist.net\/anime\/genre\/10\/Fantasy"},{"mal_id":36,"type":"anime","name":"Slice of Life","url":"https:\/\/myanimelist.net\/anime\/genre\/36\/Slice_of_Life"}],"explicit_genres":[],"themes":[],"demographics":[]},{"mal_id":50663,"url":"https:\/\/myanimelist.net\/anime\/50663\/Poputepipikku_2nd_Season","images":{"jpg":{"image_url":"https:\/\/cdn.myanimelist.net\/images\/anime\/1237\/128067.jpg","small_image_url":"https:\/\/cdn.myanimelist.net\/images\/anime\/1237\/128067t.jpg","large_image_url":"https:\/\/cdn.myanimelist.net\/images\/anime\/1237\/128067l.jpg"},"webp":{"image_url":"https:\/\/cdn.myanimelist.net\/images\/anime\/1237\/128067.webp","small_image_url":"https:\/\/cdn.myanimelist.net\/images\/anime\/1237\/128067t.webp","large_image_url":"https:\/\/cdn.myanimelist.net\/images\/anime\/1237\/128067l.webp"}},"trailer":{"youtube_id":"ZPV_toAr1ZU","url":"https:\/\/www.youtube.com\/watch?v=ZPV_toAr1ZU","embed_url":"https:\/\/www.youtube.com\/embed\/ZPV_toAr1ZU?enablejsapi=1&wmode=opaque&autoplay=1","images":{"image_url":"https:\/\/img.youtube.com\/vi\/ZPV_toAr1ZU\/default.jpg","small_image_url":"https:\/\/img.youtube.com\/vi\/ZPV_toAr1ZU\/sddefault.jpg","medium_image_url":"https:\/\/img.youtube.com\/vi\/ZPV_toAr1ZU\/mqdefault.jpg","large_image_url":"https:\/\/img.youtube.com\/vi\/ZPV_toAr1ZU\/hqdefault.jpg","maximum_image_url":"https:\/\/img.youtube.com\/vi\/ZPV_toAr1ZU\/maxresdefault.jpg"}},"approved":true,"titles":[{"type":"Default","title":"Poputepipikku 2nd Season"},{"type":"Japanese","title":"\u30dd\u30d7\u30c6\u30d4\u30d4\u30c3\u30af"},{"type":"English","title":"Pop Team Epic Season 2"}],"title":"Poputepipikku 2nd Season","title_english":"Pop Team Epic Season 2","title_japanese":"\u30dd\u30d7\u30c6\u30d4\u30d4\u30c3\u30af","title_synonyms":[],"type":"TV","source":"4-koma manga","episodes":12,"status":"Currently Airing","airing":true,"aired":{"from":"2022-10-02T00:00:00+00:00","to":null,"prop":{"from":{"day":2,"month":10,"year":2022},"to":{"day":null,"month":null,"year":null}},"string":"Oct 2, 2022 to ?"},"duration":"23 min per ep","rating":"PG-13 - Teens 13 or older","score":7.44,"scored_by":2468,"rank":1914,"popularity":3761,"members":27618,"favorites":90,"synopsis":"High school girl duo Popuko and Pipimi are back and more unhinged than ever after their initial efforts to create a full-fledged anime production were met with a great reception. With no regard for their audience, they continue to live their reckless everyday lives consisting of comedy skits and parodies of epic proportions. No one is immune to the effects of their antics\u2014including hapless live actor Shouta Aoi, who is on the run and stuck trying to be a hero in the wrong series. [Written by MAL Rewrite]","background":"Poputepipikku 2nd Season was released on Blu-ray in three volumes from November 23, 2022 to January 25, 2023.","season":"fall","year":2022,"broadcast":{"day":"Sundays","time":"01:30","timezone":"Asia\/Tokyo","string":"Sundays at 01:30 (JST)"},"producers":[{"mal_id":1344,"type":"anime","name":"King Records","url":"https:\/\/myanimelist.net\/anime\/producer\/1344\/King_Records"}],"licensors":[],"studios":[{"mal_id":437,"type":"anime","name":"Kamikaze Douga","url":"https:\/\/myanimelist.net\/anime\/producer\/437\/Kamikaze_Douga"},{"mal_id":1045,"type":"anime","name":"Space Neko Company","url":"https:\/\/myanimelist.net\/anime\/producer\/1045\/Space_Neko_Company"}],"genres":[{"mal_id":4,"type":"anime","name":"Comedy","url":"https:\/\/myanimelist.net\/anime\/genre\/4\/Comedy"}],"explicit_genres":[],"themes":[{"mal_id":57,"type":"anime","name":"Gag Humor","url":"https:\/\/myanimelist.net\/anime\/genre\/57\/Gag_Humor"},{"mal_id":20,"type":"anime","name":"Parody","url":"https:\/\/myanimelist.net\/anime\/genre\/20\/Parody"}],"demographics":[]},{"mal_id":50205,"url":"https:\/\/myanimelist.net\/anime\/50205\/Arknights__Reimei_Zensou","images":{"jpg":{"image_url":"https:\/\/cdn.myanimelist.net\/images\/anime\/1666\/129162.jpg","small_image_url":"https:\/\/cdn.myanimelist.net\/images\/anime\/1666\/129162t.jpg","large_image_url":"https:\/\/cdn.myanimelist.net\/images\/anime\/1666\/129162l.jpg"},"webp":{"image_url":"https:\/\/cdn.myanimelist.net\/images\/anime\/1666\/129162.webp","small_image_url":"https:\/\/cdn.myanimelist.net\/images\/anime\/1666\/129162t.webp","large_image_url":"https:\/\/cdn.myanimelist.net\/images\/anime\/1666\/129162l.webp"}},"trailer":{"youtube_id":"VS6rsy-tVNU","url":"https:\/\/www.youtube.com\/watch?v=VS6rsy-tVNU","embed_url":"https:\/\/www.youtube.com\/embed\/VS6rsy-tVNU?enablejsapi=1&wmode=opaque&autoplay=1","images":{"image_url":"https:\/\/img.youtube.com\/vi\/VS6rsy-tVNU\/default.jpg","small_image_url":"https:\/\/img.youtube.com\/vi\/VS6rsy-tVNU\/sddefault.jpg","medium_image_url":"https:\/\/img.youtube.com\/vi\/VS6rsy-tVNU\/mqdefault.jpg","large_image_url":"https:\/\/img.youtube.com\/vi\/VS6rsy-tVNU\/hqdefault.jpg","maximum_image_url":"https:\/\/img.youtube.com\/vi\/VS6rsy-tVNU\/maxresdefault.jpg"}},"approved":true,"titles":[{"type":"Default","title":"Arknights: Reimei Zensou"},{"type":"Synonym","title":"Arknights: Prelude to Dawn"},{"type":"Japanese","title":"\u30a2\u30fc\u30af\u30ca\u30a4\u30c4 -\u9ece\u660e\u524d\u594f-"},{"type":"English","title":"Arknights Animation: Prelude to Dawn"}],"title":"Arknights: Reimei Zensou","title_english":"Arknights Animation: Prelude to Dawn","title_japanese":"\u30a2\u30fc\u30af\u30ca\u30a4\u30c4 -\u9ece\u660e\u524d\u594f-","title_synonyms":["Arknights: Prelude to Dawn"],"type":"TV","source":"Game","episodes":8,"status":"Not yet aired","airing":false,"aired":{"from":"2022-10-29T00:00:00+00:00","to":null,"prop":{"from":{"day":29,"month":10,"year":2022},"to":{"day":null,"month":null,"year":null}},"string":"Oct 29, 2022 to ?"},"duration":"Unknown","rating":null,"score":null,"scored_by":null,"rank":null,"popularity":3869,"members":26011,"favorites":286,"synopsis":"In the land of Terra, natural disasters of unknown causes have been occurring irregularly in many areas. Therefore, the majority of the people, in order to escape those natural disasters, came to live in mobile cities developed over the years. The Originium left behind at the site of such Catastrophes, has led to the rapid progress of civilization due to their immense energy. But it also brought something else with it \u2014 an incurable disease called Oripathy. Because the bodies of those with Oripathy gradually crystalize and become a new source of infection at the time of death, in many countries, the Infected are subject to persecution under regimes of segregation and forced labor. Those who were oppressed by the governments are starting to rebel. Rhodes Island, a pharmaceutical company researching a cure for Oripathy, takes up their arms and starts a conquest trying to save all the people from the disease. (Source: Official Site, translated, edited)","background":"Adaptation of Hypergryph's Arknights smartphone game.","season":"fall","year":2022,"broadcast":{"day":"Saturdays","time":"01:23","timezone":"Asia\/Tokyo","string":"Saturdays at 01:23 (JST)"},"producers":[],"licensors":[],"studios":[{"mal_id":2009,"type":"anime","name":"Yostar Pictures","url":"https:\/\/myanimelist.net\/anime\/producer\/2009\/Yostar_Pictures"}],"genres":[{"mal_id":1,"type":"anime","name":"Action","url":"https:\/\/myanimelist.net\/anime\/genre\/1\/Action"},{"mal_id":10,"type":"anime","name":"Fantasy","url":"https:\/\/myanimelist.net\/anime\/genre\/10\/Fantasy"}],"explicit_genres":[],"themes":[],"demographics":[]},{"mal_id":51680,"url":"https:\/\/myanimelist.net\/anime\/51680\/Cool_Doji_Danshi","images":{"jpg":{"image_url":"https:\/\/cdn.myanimelist.net\/images\/anime\/1779\/127719.jpg","small_image_url":"https:\/\/cdn.myanimelist.net\/images\/anime\/1779\/127719t.jpg","large_image_url":"https:\/\/cdn.myanimelist.net\/images\/anime\/1779\/127719l.jpg"},"webp":{"image_url":"https:\/\/cdn.myanimelist.net\/images\/anime\/1779\/127719.webp","small_image_url":"https:\/\/cdn.myanimelist.net\/images\/anime\/1779\/127719t.webp","large_image_url":"https:\/\/cdn.myanimelist.net\/images\/anime\/1779\/127719l.webp"}},"trailer":{"youtube_id":"o8Ig5Bt8kCw","url":"https:\/\/www.youtube.com\/watch?v=o8Ig5Bt8kCw","embed_url":"https:\/\/www.youtube.com\/embed\/o8Ig5Bt8kCw?enablejsapi=1&wmode=opaque&autoplay=1","images":{"image_url":"https:\/\/img.youtube.com\/vi\/o8Ig5Bt8kCw\/default.jpg","small_image_url":"https:\/\/img.youtube.com\/vi\/o8Ig5Bt8kCw\/sddefault.jpg","medium_image_url":"https:\/\/img.youtube.com\/vi\/o8Ig5Bt8kCw\/mqdefault.jpg","large_image_url":"https:\/\/img.youtube.com\/vi\/o8Ig5Bt8kCw\/hqdefault.jpg","maximum_image_url":"https:\/\/img.youtube.com\/vi\/o8Ig5Bt8kCw\/maxresdefault.jpg"}},"approved":true,"titles":[{"type":"Default","title":"Cool Doji Danshi"},{"type":"Japanese","title":"\u30af\u30fc\u30eb\u30c9\u30b8\u7537\u5b50"},{"type":"English","title":"Play It Cool, Guys"}],"title":"Cool Doji Danshi","title_english":"Play It Cool, Guys","title_japanese":"\u30af\u30fc\u30eb\u30c9\u30b8\u7537\u5b50","title_synonyms":[],"type":"TV","source":"Web manga","episodes":null,"status":"Currently Airing","airing":true,"aired":{"from":"2022-10-11T00:00:00+00:00","to":null,"prop":{"from":{"day":11,"month":10,"year":2022},"to":{"day":null,"month":null,"year":null}},"string":"Oct 11, 2022 to ?"},"duration":"11 min","rating":"PG-13 - Teens 13 or older","score":7.2,"scored_by":1628,"rank":2989,"popularity":3869,"members":25984,"favorites":170,"synopsis":"They are handsome guys who are cool but a little hard to approach. However, they...are all clumsy!!! Because they are clumsy, they're relatable. Because they are clumsy, they're adorable. You'll surely come to love them too! A slice of life comedy about guys who stay cool despite being clumsy! (Source: Square Enix, translated)","background":null,"season":"fall","year":2022,"broadcast":{"day":"Tuesdays","time":"01:30","timezone":"Asia\/Tokyo","string":"Tuesdays at 01:30 (JST)"},"producers":[{"mal_id":306,"type":"anime","name":"Magic Capsule","url":"https:\/\/myanimelist.net\/anime\/producer\/306\/Magic_Capsule"},{"mal_id":1284,"type":"anime","name":"Avex Pictures","url":"https:\/\/myanimelist.net\/anime\/producer\/1284\/Avex_Pictures"}],"licensors":[],"studios":[{"mal_id":1,"type":"anime","name":"Pierrot","url":"https:\/\/myanimelist.net\/anime\/producer\/1\/Pierrot"}],"genres":[{"mal_id":4,"type":"anime","name":"Comedy","url":"https:\/\/myanimelist.net\/anime\/genre\/4\/Comedy"}],"explicit_genres":[],"themes":[],"demographics":[]},{"mal_id":51306,"url":"https:\/\/myanimelist.net\/anime\/51306\/C_Danchi","images":{"jpg":{"image_url":"https:\/\/cdn.myanimelist.net\/images\/anime\/1378\/121573.jpg","small_image_url":"https:\/\/cdn.myanimelist.net\/images\/anime\/1378\/121573t.jpg","large_image_url":"https:\/\/cdn.myanimelist.net\/images\/anime\/1378\/121573l.jpg"},"webp":{"image_url":"https:\/\/cdn.myanimelist.net\/images\/anime\/1378\/121573.webp","small_image_url":"https:\/\/cdn.myanimelist.net\/images\/anime\/1378\/121573t.webp","large_image_url":"https:\/\/cdn.myanimelist.net\/images\/anime\/1378\/121573l.webp"}},"trailer":{"youtube_id":"zhyGKfW8Sv4","url":"https:\/\/www.youtube.com\/watch?v=zhyGKfW8Sv4","embed_url":"https:\/\/www.youtube.com\/embed\/zhyGKfW8Sv4?enablejsapi=1&wmode=opaque&autoplay=1","images":{"image_url":"https:\/\/img.youtube.com\/vi\/zhyGKfW8Sv4\/default.jpg","small_image_url":"https:\/\/img.youtube.com\/vi\/zhyGKfW8Sv4\/sddefault.jpg","medium_image_url":"https:\/\/img.youtube.com\/vi\/zhyGKfW8Sv4\/mqdefault.jpg","large_image_url":"https:\/\/img.youtube.com\/vi\/zhyGKfW8Sv4\/hqdefault.jpg","maximum_image_url":"https:\/\/img.youtube.com\/vi\/zhyGKfW8Sv4\/maxresdefault.jpg"}},"approved":true,"titles":[{"type":"Default","title":"C Danchi"},{"type":"Japanese","title":"C\u56e3\u5730"},{"type":"English","title":"Housing Complex C"}],"title":"C Danchi","title_english":"Housing Complex C","title_japanese":"C\u56e3\u5730","title_synonyms":[],"type":"TV","source":"Original","episodes":4,"status":"Finished Airing","airing":false,"aired":{"from":"2022-10-02T00:00:00+00:00","to":"2022-10-23T00:00:00+00:00","prop":{"from":{"day":2,"month":10,"year":2022},"to":{"day":23,"month":10,"year":2022}},"string":"Oct 2, 2022 to Oct 23, 2022"},"duration":"25 min per ep","rating":"R - 17+ (violence & profanity)","score":5.43,"scored_by":2698,"rank":11486,"popularity":4488,"members":18673,"favorites":78,"synopsis":"\"Housing Complex C\" centers around Kimi, who lives in a small, low-cost housing complex located in the seaside town of Kurosaki. Trouble seems to follow her wherever she goes, and horrific incidents begin to occur. Is an ancient evil stalking the residents of Housing Complex C? (Source: Variety, edited)","background":null,"season":"fall","year":2022,"broadcast":{"day":"Sundays","time":"13:00","timezone":"Asia\/Tokyo","string":"Sundays at 13:00 (JST)"},"producers":[{"mal_id":10,"type":"anime","name":"Production I.G","url":"https:\/\/myanimelist.net\/anime\/producer\/10\/Production_IG"}],"licensors":[],"studios":[{"mal_id":2034,"type":"anime","name":"Akatsuki","url":"https:\/\/myanimelist.net\/anime\/producer\/2034\/Akatsuki"}],"genres":[{"mal_id":14,"type":"anime","name":"Horror","url":"https:\/\/myanimelist.net\/anime\/genre\/14\/Horror"}],"explicit_genres":[],"themes":[],"demographics":[]},{"mal_id":51464,"url":"https:\/\/myanimelist.net\/anime\/51464\/4-nin_wa_Sorezore_Uso_wo_Tsuku","images":{"jpg":{"image_url":"https:\/\/cdn.myanimelist.net\/images\/anime\/1934\/128719.jpg","small_image_url":"https:\/\/cdn.myanimelist.net\/images\/anime\/1934\/128719t.jpg","large_image_url":"https:\/\/cdn.myanimelist.net\/images\/anime\/1934\/128719l.jpg"},"webp":{"image_url":"https:\/\/cdn.myanimelist.net\/images\/anime\/1934\/128719.webp","small_image_url":"https:\/\/cdn.myanimelist.net\/images\/anime\/1934\/128719t.webp","large_image_url":"https:\/\/cdn.myanimelist.net\/images\/anime\/1934\/128719l.webp"}},"trailer":{"youtube_id":"6KPCyMQ5oNg","url":"https:\/\/www.youtube.com\/watch?v=6KPCyMQ5oNg","embed_url":"https:\/\/www.youtube.com\/embed\/6KPCyMQ5oNg?enablejsapi=1&wmode=opaque&autoplay=1","images":{"image_url":"https:\/\/img.youtube.com\/vi\/6KPCyMQ5oNg\/default.jpg","small_image_url":"https:\/\/img.youtube.com\/vi\/6KPCyMQ5oNg\/sddefault.jpg","medium_image_url":"https:\/\/img.youtube.com\/vi\/6KPCyMQ5oNg\/mqdefault.jpg","large_image_url":"https:\/\/img.youtube.com\/vi\/6KPCyMQ5oNg\/hqdefault.jpg","maximum_image_url":"https:\/\/img.youtube.com\/vi\/6KPCyMQ5oNg\/maxresdefault.jpg"}},"approved":true,"titles":[{"type":"Default","title":"4-nin wa Sorezore Uso wo Tsuku"},{"type":"Synonym","title":"Four People and Their Respective Lies"},{"type":"Japanese","title":"\uff14\u4eba\u306f\u305d\u308c\u305e\u308c\u30a6\u30bd\u3092\u3064\u304f"},{"type":"English","title":"The Little Lies We All Tell"}],"title":"4-nin wa Sorezore Uso wo Tsuku","title_english":"The Little Lies We All Tell","title_japanese":"\uff14\u4eba\u306f\u305d\u308c\u305e\u308c\u30a6\u30bd\u3092\u3064\u304f","title_synonyms":["Four People and Their Respective Lies"],"type":"TV","source":"Manga","episodes":11,"status":"Currently Airing","airing":true,"aired":{"from":"2022-10-16T00:00:00+00:00","to":null,"prop":{"from":{"day":16,"month":10,"year":2022},"to":{"day":null,"month":null,"year":null}},"string":"Oct 16, 2022 to ?"},"duration":"23 min per ep","rating":"PG-13 - Teens 13 or older","score":6.81,"scored_by":1960,"rank":4758,"popularity":4538,"members":18213,"favorites":56,"synopsis":"The story of four friends who each have a secret they cannot share with each other.","background":null,"season":"fall","year":2022,"broadcast":{"day":"Sundays","time":"02:00","timezone":"Asia\/Tokyo","string":"Sundays at 02:00 (JST)"},"producers":[{"mal_id":1,"type":"anime","name":"Pierrot","url":"https:\/\/myanimelist.net\/anime\/producer\/1\/Pierrot"},{"mal_id":159,"type":"anime","name":"Kodansha","url":"https:\/\/myanimelist.net\/anime\/producer\/159\/Kodansha"},{"mal_id":1500,"type":"anime","name":"ABC Animation","url":"https:\/\/myanimelist.net\/anime\/producer\/1500\/ABC_Animation"},{"mal_id":2618,"type":"anime","name":"MediBang","url":"https:\/\/myanimelist.net\/anime\/producer\/2618\/MediBang"}],"licensors":[],"studios":[{"mal_id":1693,"type":"anime","name":"Studio Flad","url":"https:\/\/myanimelist.net\/anime\/producer\/1693\/Studio_Flad"}],"genres":[{"mal_id":4,"type":"anime","name":"Comedy","url":"https:\/\/myanimelist.net\/anime\/genre\/4\/Comedy"}],"explicit_genres":[],"themes":[{"mal_id":57,"type":"anime","name":"Gag Humor","url":"https:\/\/myanimelist.net\/anime\/genre\/57\/Gag_Humor"},{"mal_id":23,"type":"anime","name":"School","url":"https:\/\/myanimelist.net\/anime\/genre\/23\/School"}],"demographics":[{"mal_id":27,"type":"anime","name":"Shounen","url":"https:\/\/myanimelist.net\/anime\/genre\/27\/Shounen"}]},{"mal_id":49533,"url":"https:\/\/myanimelist.net\/anime\/49533\/Uchi_no_Shishou_wa_Shippo_ga_Nai","images":{"jpg":{"image_url":"https:\/\/cdn.myanimelist.net\/images\/anime\/1289\/127754.jpg","small_image_url":"https:\/\/cdn.myanimelist.net\/images\/anime\/1289\/127754t.jpg","large_image_url":"https:\/\/cdn.myanimelist.net\/images\/anime\/1289\/127754l.jpg"},"webp":{"image_url":"https:\/\/cdn.myanimelist.net\/images\/anime\/1289\/127754.webp","small_image_url":"https:\/\/cdn.myanimelist.net\/images\/anime\/1289\/127754t.webp","large_image_url":"https:\/\/cdn.myanimelist.net\/images\/anime\/1289\/127754l.webp"}},"trailer":{"youtube_id":"pRP4VDqWXVw","url":"https:\/\/www.youtube.com\/watch?v=pRP4VDqWXVw","embed_url":"https:\/\/www.youtube.com\/embed\/pRP4VDqWXVw?enablejsapi=1&wmode=opaque&autoplay=1","images":{"image_url":"https:\/\/img.youtube.com\/vi\/pRP4VDqWXVw\/default.jpg","small_image_url":"https:\/\/img.youtube.com\/vi\/pRP4VDqWXVw\/sddefault.jpg","medium_image_url":"https:\/\/img.youtube.com\/vi\/pRP4VDqWXVw\/mqdefault.jpg","large_image_url":"https:\/\/img.youtube.com\/vi\/pRP4VDqWXVw\/hqdefault.jpg","maximum_image_url":"https:\/\/img.youtube.com\/vi\/pRP4VDqWXVw\/maxresdefault.jpg"}},"approved":true,"titles":[{"type":"Default","title":"Uchi no Shishou wa Shippo ga Nai"},{"type":"Japanese","title":"\u3046\u3061\u306e\u5e2b\u5320\u306f\u3057\u3063\u307d\u304c\u306a\u3044"},{"type":"English","title":"My Master Has No Tail"}],"title":"Uchi no Shishou wa Shippo ga Nai","title_english":"My Master Has No Tail","title_japanese":"\u3046\u3061\u306e\u5e2b\u5320\u306f\u3057\u3063\u307d\u304c\u306a\u3044","title_synonyms":[],"type":"TV","source":"Manga","episodes":13,"status":"Currently Airing","airing":true,"aired":{"from":"2022-09-30T00:00:00+00:00","to":null,"prop":{"from":{"day":30,"month":9,"year":2022},"to":{"day":null,"month":null,"year":null}},"string":"Sep 30, 2022 to ?"},"duration":"23 min per ep","rating":"PG-13 - Teens 13 or older","score":6.31,"scored_by":1983,"rank":7502,"popularity":4853,"members":15378,"favorites":19,"synopsis":"The beginning of the Meiji era spelled the end of the tanuki's tricks. These raccoon dogs, who are able to transform into human beings, used to love fooling humans until advanced technology rendered their endeavors futile. However, Mameda, a young tanuki girl, has not given up on this tradition, and\u2014resolved to follow in her father's footsteps\u2014travels to Osaka in hopes of duping people. As others in her village predicted, Mameda fails to deceive a single person, and she is even hunted down by an angry crowd. After finding refuge in a theater, she stumbles upon a rakugo performance given by a master of the art, Bunko Daikokutei. Fascinated by the vivid images created by the rakugoka's acting, Mameda becomes enamored with this style of storytelling and decides to become Bunko's apprentice! Despite her initial reluctance to take a disciple, Bunko begins to teach Mameda rakugo after witnessing the young tanuki's perseverance. Between undertaking a taiko apprenticeship, handling her work at the theater, and memorizing plays, Mameda needs to give her all if she ever plans to master the only art that still has a chance to fool people. [Written by MAL Rewrite]","background":"Uchi no Shishou wa Shippo ga Nai was released on Blu-ray in a standard and limited edition box by Pony Canyon on January 18, 2023.","season":"fall","year":2022,"broadcast":{"day":"Fridays","time":"22:30","timezone":"Asia\/Tokyo","string":"Fridays at 22:30 (JST)"},"producers":[{"mal_id":1,"type":"anime","name":"Pierrot","url":"https:\/\/myanimelist.net\/anime\/producer\/1\/Pierrot"},{"mal_id":73,"type":"anime","name":"TMS Entertainment","url":"https:\/\/myanimelist.net\/anime\/producer\/73\/TMS_Entertainment"},{"mal_id":143,"type":"anime","name":"Mainichi Broadcasting System","url":"https:\/\/myanimelist.net\/anime\/producer\/143\/Mainichi_Broadcasting_System"},{"mal_id":144,"type":"anime","name":"Pony Canyon","url":"https:\/\/myanimelist.net\/anime\/producer\/144\/Pony_Canyon"},{"mal_id":2009,"type":"anime","name":"Yostar Pictures","url":"https:\/\/myanimelist.net\/anime\/producer\/2009\/Yostar_Pictures"},{"mal_id":2185,"type":"anime","name":"BS Asahi","url":"https:\/\/myanimelist.net\/anime\/producer\/2185\/BS_Asahi"}],"licensors":[{"mal_id":376,"type":"anime","name":"Sentai Filmworks","url":"https:\/\/myanimelist.net\/anime\/producer\/376\/Sentai_Filmworks"}],"studios":[{"mal_id":839,"type":"anime","name":"LIDENFILMS","url":"https:\/\/myanimelist.net\/anime\/producer\/839\/LIDENFILMS"}],"genres":[{"mal_id":37,"type":"anime","name":"Supernatural","url":"https:\/\/myanimelist.net\/anime\/genre\/37\/Supernatural"}],"explicit_genres":[],"themes":[{"mal_id":13,"type":"anime","name":"Historical","url":"https:\/\/myanimelist.net\/anime\/genre\/13\/Historical"},{"mal_id":70,"type":"anime","name":"Performing Arts","url":"https:\/\/myanimelist.net\/anime\/genre\/70\/Performing_Arts"}],"demographics":[{"mal_id":42,"type":"anime","name":"Seinen","url":"https:\/\/myanimelist.net\/anime\/genre\/42\/Seinen"}]},{"mal_id":52976,"url":"https:\/\/myanimelist.net\/anime\/52976\/Berserk__Ougon_Jidai-hen_-_Memorial_Edition","images":{"jpg":{"image_url":"https:\/\/cdn.myanimelist.net\/images\/anime\/1607\/127730.jpg","small_image_url":"https:\/\/cdn.myanimelist.net\/images\/anime\/1607\/127730t.jpg","large_image_url":"https:\/\/cdn.myanimelist.net\/images\/anime\/1607\/127730l.jpg"},"webp":{"image_url":"https:\/\/cdn.myanimelist.net\/images\/anime\/1607\/127730.webp","small_image_url":"https:\/\/cdn.myanimelist.net\/images\/anime\/1607\/127730t.webp","large_image_url":"https:\/\/cdn.myanimelist.net\/images\/anime\/1607\/127730l.webp"}},"trailer":{"youtube_id":"H6dkuEdzaFY","url":"https:\/\/www.youtube.com\/watch?v=H6dkuEdzaFY","embed_url":"https:\/\/www.youtube.com\/embed\/H6dkuEdzaFY?enablejsapi=1&wmode=opaque&autoplay=1","images":{"image_url":"https:\/\/img.youtube.com\/vi\/H6dkuEdzaFY\/default.jpg","small_image_url":"https:\/\/img.youtube.com\/vi\/H6dkuEdzaFY\/sddefault.jpg","medium_image_url":"https:\/\/img.youtube.com\/vi\/H6dkuEdzaFY\/mqdefault.jpg","large_image_url":"https:\/\/img.youtube.com\/vi\/H6dkuEdzaFY\/hqdefault.jpg","maximum_image_url":"https:\/\/img.youtube.com\/vi\/H6dkuEdzaFY\/maxresdefault.jpg"}},"approved":true,"titles":[{"type":"Default","title":"Berserk: Ougon Jidai-hen - Memorial Edition"},{"type":"Japanese","title":"\u30d9\u30eb\u30bb\u30eb\u30af \u9ec4\u91d1\u6642\u4ee3\u7bc7\u3000MEMORIAL EDITION"},{"type":"English","title":"Berserk: The Golden Age Arc - Memorial Edition"}],"title":"Berserk: Ougon Jidai-hen - Memorial Edition","title_english":"Berserk: The Golden Age Arc - Memorial Edition","title_japanese":"\u30d9\u30eb\u30bb\u30eb\u30af \u9ec4\u91d1\u6642\u4ee3\u7bc7\u3000MEMORIAL EDITION","title_synonyms":[],"type":"TV","source":"Manga","episodes":null,"status":"Currently Airing","airing":true,"aired":{"from":"2022-10-02T00:00:00+00:00","to":null,"prop":{"from":{"day":2,"month":10,"year":2022},"to":{"day":null,"month":null,"year":null}},"string":"Oct 2, 2022 to ?"},"duration":"25 min","rating":"R+ - Mild Nudity","score":7.55,"scored_by":2644,"rank":1512,"popularity":4860,"members":15325,"favorites":67,"synopsis":"TV edit of the Berserk: The Golden Age Arc film trilogy. He has believed only in his own sword. With no friends, no family, and no home to return to, Guts is a lonely swordsman who travels around as a mercenary in a land shaken by the Hundred Years War. Guts is able to handle a sword longer than he is tall and easily defeats powerful enemies. Griffith, the leader of the mercenary group \"Band of the Hawk,\" has his eye on Guts. Griffith, who has a commanding power unimaginable from his beautiful appearance and great ambitions, wins Guts in a duel and brings him into the Band of the Hawk to fulfill his own dream. As they go through numerous fierce battles together, their friends become bound by trust. The bond between Griffith and Guts, in particular, has become something special. Eventually, the Band of the Hawk rose to become the regular army of the Kingdom of Midland, but this was only the first step in Griffith's quest to reach the top. Guts, on the other hand, is taken in by Griffith's \"dream\" and begins to question his life of just wielding a sword. But what Guts doesn't know yet is the terrible fate that their endless dreams have bestowed upon them...","background":"In this TV broadcast, the \"Bonfire of Dreams\", one of the most popular scenes in the original work, which was not in the 2012 theatrical version, is added as a completely new cut under the supervision of Naoyuki Onda, Chief Animation Director, just like in the theatrical version. In addition, hundreds of existing cuts have been reworked and updated as remastered versions. The new cuts will feature music by Susumu Hirasawa and Shiro Sagisu.","season":"fall","year":2022,"broadcast":{"day":"Sundays","time":"00:30","timezone":"Asia\/Tokyo","string":"Sundays at 00:30 (JST)"},"producers":[{"mal_id":17,"type":"anime","name":"Aniplex","url":"https:\/\/myanimelist.net\/anime\/producer\/17\/Aniplex"},{"mal_id":29,"type":"anime","name":"VAP","url":"https:\/\/myanimelist.net\/anime\/producer\/29\/VAP"},{"mal_id":148,"type":"anime","name":"Hakusensha","url":"https:\/\/myanimelist.net\/anime\/producer\/148\/Hakusensha"},{"mal_id":166,"type":"anime","name":"Movic","url":"https:\/\/myanimelist.net\/anime\/producer\/166\/Movic"},{"mal_id":795,"type":"anime","name":"Yahoo! Japan","url":"https:\/\/myanimelist.net\/anime\/producer\/795\/Yahoo_Japan"},{"mal_id":1261,"type":"anime","name":"Good Smile Company","url":"https:\/\/myanimelist.net\/anime\/producer\/1261\/Good_Smile_Company"},{"mal_id":1584,"type":"anime","name":"Beyond C.","url":"https:\/\/myanimelist.net\/anime\/producer\/1584\/Beyond_C"},{"mal_id":1697,"type":"anime","name":"KDDI","url":"https:\/\/myanimelist.net\/anime\/producer\/1697\/KDDI"},{"mal_id":2018,"type":"anime","name":"Rialto Entertainment","url":"https:\/\/myanimelist.net\/anime\/producer\/2018\/Rialto_Entertainment"}],"licensors":[],"studios":[{"mal_id":13,"type":"anime","name":"Studio 4\u00b0C","url":"https:\/\/myanimelist.net\/anime\/producer\/13\/Studio_4%C2%B0C"}],"genres":[{"mal_id":1,"type":"anime","name":"Action","url":"https:\/\/myanimelist.net\/anime\/genre\/1\/Action"},{"mal_id":8,"type":"anime","name":"Drama","url":"https:\/\/myanimelist.net\/anime\/genre\/8\/Drama"},{"mal_id":10,"type":"anime","name":"Fantasy","url":"https:\/\/myanimelist.net\/anime\/genre\/10\/Fantasy"},{"mal_id":14,"type":"anime","name":"Horror","url":"https:\/\/myanimelist.net\/anime\/genre\/14\/Horror"},{"mal_id":37,"type":"anime","name":"Supernatural","url":"https:\/\/myanimelist.net\/anime\/genre\/37\/Supernatural"}],"explicit_genres":[],"themes":[{"mal_id":58,"type":"anime","name":"Gore","url":"https:\/\/myanimelist.net\/anime\/genre\/58\/Gore"},{"mal_id":38,"type":"anime","name":"Military","url":"https:\/\/myanimelist.net\/anime\/genre\/38\/Military"},{"mal_id":6,"type":"anime","name":"Mythology","url":"https:\/\/myanimelist.net\/anime\/genre\/6\/Mythology"}],"demographics":[{"mal_id":42,"type":"anime","name":"Seinen","url":"https:\/\/myanimelist.net\/anime\/genre\/42\/Seinen"}]},{"mal_id":50552,"url":"https:\/\/myanimelist.net\/anime\/50552\/Yowamushi_Pedal__Limit_Break","images":{"jpg":{"image_url":"https:\/\/cdn.myanimelist.net\/images\/anime\/1000\/127332.jpg","small_image_url":"https:\/\/cdn.myanimelist.net\/images\/anime\/1000\/127332t.jpg","large_image_url":"https:\/\/cdn.myanimelist.net\/images\/anime\/1000\/127332l.jpg"},"webp":{"image_url":"https:\/\/cdn.myanimelist.net\/images\/anime\/1000\/127332.webp","small_image_url":"https:\/\/cdn.myanimelist.net\/images\/anime\/1000\/127332t.webp","large_image_url":"https:\/\/cdn.myanimelist.net\/images\/anime\/1000\/127332l.webp"}},"trailer":{"youtube_id":"KLdllQiQX58","url":"https:\/\/www.youtube.com\/watch?v=KLdllQiQX58","embed_url":"https:\/\/www.youtube.com\/embed\/KLdllQiQX58?enablejsapi=1&wmode=opaque&autoplay=1","images":{"image_url":"https:\/\/img.youtube.com\/vi\/KLdllQiQX58\/default.jpg","small_image_url":"https:\/\/img.youtube.com\/vi\/KLdllQiQX58\/sddefault.jpg","medium_image_url":"https:\/\/img.youtube.com\/vi\/KLdllQiQX58\/mqdefault.jpg","large_image_url":"https:\/\/img.youtube.com\/vi\/KLdllQiQX58\/hqdefault.jpg","maximum_image_url":"https:\/\/img.youtube.com\/vi\/KLdllQiQX58\/maxresdefault.jpg"}},"approved":true,"titles":[{"type":"Default","title":"Yowamushi Pedal: Limit Break"},{"type":"Synonym","title":"Yowamushi Pedal 5th Season"},{"type":"Synonym","title":"Yowapeda 5th Season"},{"type":"Japanese","title":"\u5f31\u866b\u30da\u30c0\u30eb LIMIT BREAK"}],"title":"Yowamushi Pedal: Limit Break","title_english":null,"title_japanese":"\u5f31\u866b\u30da\u30c0\u30eb LIMIT BREAK","title_synonyms":["Yowamushi Pedal 5th Season","Yowapeda 5th Season"],"type":"TV","source":"Manga","episodes":null,"status":"Currently Airing","airing":true,"aired":{"from":"2022-10-09T00:00:00+00:00","to":null,"prop":{"from":{"day":9,"month":10,"year":2022},"to":{"day":null,"month":null,"year":null}},"string":"Oct 9, 2022 to ?"},"duration":"24 min","rating":"PG-13 - Teens 13 or older","score":7.57,"scored_by":1097,"rank":1452,"popularity":4940,"members":14692,"favorites":101,"synopsis":"Fifth season of the Yowamushi Pedal series.","background":null,"season":"fall","year":2022,"broadcast":{"day":"Sundays","time":"00:00","timezone":"Asia\/Tokyo","string":"Sundays at 00:00 (JST)"},"producers":[{"mal_id":16,"type":"anime","name":"TV Tokyo","url":"https:\/\/myanimelist.net\/anime\/producer\/16\/TV_Tokyo"},{"mal_id":135,"type":"anime","name":"MediaNet","url":"https:\/\/myanimelist.net\/anime\/producer\/135\/MediaNet"},{"mal_id":1143,"type":"anime","name":"TOHO animation","url":"https:\/\/myanimelist.net\/anime\/producer\/1143\/TOHO_animation"},{"mal_id":1373,"type":"anime","name":"Akita Shoten","url":"https:\/\/myanimelist.net\/anime\/producer\/1373\/Akita_Shoten"},{"mal_id":1797,"type":"anime","name":"NHK Enterprises","url":"https:\/\/myanimelist.net\/anime\/producer\/1797\/NHK_Enterprises"}],"licensors":[],"studios":[{"mal_id":73,"type":"anime","name":"TMS Entertainment","url":"https:\/\/myanimelist.net\/anime\/producer\/73\/TMS_Entertainment"}],"genres":[{"mal_id":30,"type":"anime","name":"Sports","url":"https:\/\/myanimelist.net\/anime\/genre\/30\/Sports"}],"explicit_genres":[],"themes":[],"demographics":[{"mal_id":27,"type":"anime","name":"Shounen","url":"https:\/\/myanimelist.net\/anime\/genre\/27\/Shounen"}]},{"mal_id":48491,"url":"https:\/\/myanimelist.net\/anime\/48491\/Yama_no_Susume__Next_Summit","images":{"jpg":{"image_url":"https:\/\/cdn.myanimelist.net\/images\/anime\/1942\/126897.jpg","small_image_url":"https:\/\/cdn.myanimelist.net\/images\/anime\/1942\/126897t.jpg","large_image_url":"https:\/\/cdn.myanimelist.net\/images\/anime\/1942\/126897l.jpg"},"webp":{"image_url":"https:\/\/cdn.myanimelist.net\/images\/anime\/1942\/126897.webp","small_image_url":"https:\/\/cdn.myanimelist.net\/images\/anime\/1942\/126897t.webp","large_image_url":"https:\/\/cdn.myanimelist.net\/images\/anime\/1942\/126897l.webp"}},"trailer":{"youtube_id":"dklTEkcRxEc","url":"https:\/\/www.youtube.com\/watch?v=dklTEkcRxEc","embed_url":"https:\/\/www.youtube.com\/embed\/dklTEkcRxEc?enablejsapi=1&wmode=opaque&autoplay=1","images":{"image_url":"https:\/\/img.youtube.com\/vi\/dklTEkcRxEc\/default.jpg","small_image_url":"https:\/\/img.youtube.com\/vi\/dklTEkcRxEc\/sddefault.jpg","medium_image_url":"https:\/\/img.youtube.com\/vi\/dklTEkcRxEc\/mqdefault.jpg","large_image_url":"https:\/\/img.youtube.com\/vi\/dklTEkcRxEc\/hqdefault.jpg","maximum_image_url":"https:\/\/img.youtube.com\/vi\/dklTEkcRxEc\/maxresdefault.jpg"}},"approved":true,"titles":[{"type":"Default","title":"Yama no Susume: Next Summit"},{"type":"Japanese","title":"\u30e4\u30de\u30ce\u30b9\u30b9\u30e1 Next Summit"},{"type":"English","title":"Encouragement of Climb: Next Summit"}],"title":"Yama no Susume: Next Summit","title_english":"Encouragement of Climb: Next Summit","title_japanese":"\u30e4\u30de\u30ce\u30b9\u30b9\u30e1 Next Summit","title_synonyms":[],"type":"TV","source":"Manga","episodes":12,"status":"Currently Airing","airing":true,"aired":{"from":"2022-10-05T00:00:00+00:00","to":null,"prop":{"from":{"day":5,"month":10,"year":2022},"to":{"day":null,"month":null,"year":null}},"string":"Oct 5, 2022 to ?"},"duration":"24 min per ep","rating":"PG-13 - Teens 13 or older","score":7.16,"scored_by":1078,"rank":3247,"popularity":4993,"members":14230,"favorites":35,"synopsis":"New Yama no Susume anime.","background":null,"season":"fall","year":2022,"broadcast":{"day":"Wednesdays","time":"00:30","timezone":"Asia\/Tokyo","string":"Wednesdays at 00:30 (JST)"},"producers":[{"mal_id":925,"type":"anime","name":"Earth Star Entertainment","url":"https:\/\/myanimelist.net\/anime\/producer\/925\/Earth_Star_Entertainment"},{"mal_id":1261,"type":"anime","name":"Good Smile Company","url":"https:\/\/myanimelist.net\/anime\/producer\/1261\/Good_Smile_Company"},{"mal_id":1344,"type":"anime","name":"King Records","url":"https:\/\/myanimelist.net\/anime\/producer\/1344\/King_Records"},{"mal_id":1696,"type":"anime","name":"Kadokawa","url":"https:\/\/myanimelist.net\/anime\/producer\/1696\/Kadokawa"},{"mal_id":2017,"type":"anime","name":"Culture Entertainment","url":"https:\/\/myanimelist.net\/anime\/producer\/2017\/Culture_Entertainment"}],"licensors":[{"mal_id":376,"type":"anime","name":"Sentai Filmworks","url":"https:\/\/myanimelist.net\/anime\/producer\/376\/Sentai_Filmworks"}],"studios":[{"mal_id":441,"type":"anime","name":"8bit","url":"https:\/\/myanimelist.net\/anime\/producer\/441\/8bit"}],"genres":[{"mal_id":2,"type":"anime","name":"Adventure","url":"https:\/\/myanimelist.net\/anime\/genre\/2\/Adventure"},{"mal_id":4,"type":"anime","name":"Comedy","url":"https:\/\/myanimelist.net\/anime\/genre\/4\/Comedy"},{"mal_id":36,"type":"anime","name":"Slice of Life","url":"https:\/\/myanimelist.net\/anime\/genre\/36\/Slice_of_Life"}],"explicit_genres":[],"themes":[{"mal_id":52,"type":"anime","name":"CGDCT","url":"https:\/\/myanimelist.net\/anime\/genre\/52\/CGDCT"},{"mal_id":63,"type":"anime","name":"Iyashikei","url":"https:\/\/myanimelist.net\/anime\/genre\/63\/Iyashikei"}],"demographics":[]},{"mal_id":49304,"url":"https:\/\/myanimelist.net\/anime\/49304\/Seiken_Densetsu__Legend_of_Mana_-_The_Teardrop_Crystal","images":{"jpg":{"image_url":"https:\/\/cdn.myanimelist.net\/images\/anime\/1637\/123397.jpg","small_image_url":"https:\/\/cdn.myanimelist.net\/images\/anime\/1637\/123397t.jpg","large_image_url":"https:\/\/cdn.myanimelist.net\/images\/anime\/1637\/123397l.jpg"},"webp":{"image_url":"https:\/\/cdn.myanimelist.net\/images\/anime\/1637\/123397.webp","small_image_url":"https:\/\/cdn.myanimelist.net\/images\/anime\/1637\/123397t.webp","large_image_url":"https:\/\/cdn.myanimelist.net\/images\/anime\/1637\/123397l.webp"}},"trailer":{"youtube_id":"fghzYfngr1w","url":"https:\/\/www.youtube.com\/watch?v=fghzYfngr1w","embed_url":"https:\/\/www.youtube.com\/embed\/fghzYfngr1w?enablejsapi=1&wmode=opaque&autoplay=1","images":{"image_url":"https:\/\/img.youtube.com\/vi\/fghzYfngr1w\/default.jpg","small_image_url":"https:\/\/img.youtube.com\/vi\/fghzYfngr1w\/sddefault.jpg","medium_image_url":"https:\/\/img.youtube.com\/vi\/fghzYfngr1w\/mqdefault.jpg","large_image_url":"https:\/\/img.youtube.com\/vi\/fghzYfngr1w\/hqdefault.jpg","maximum_image_url":"https:\/\/img.youtube.com\/vi\/fghzYfngr1w\/maxresdefault.jpg"}},"approved":true,"titles":[{"type":"Default","title":"Seiken Densetsu: Legend of Mana - The Teardrop Crystal"},{"type":"Japanese","title":"\u8056\u5263\u4f1d\u8aac Legend of Mana -The Teardrop Crystal-"},{"type":"English","title":"Legend of Mana -The Teardrop Crystal-"}],"title":"Seiken Densetsu: Legend of Mana - The Teardrop Crystal","title_english":"Legend of Mana -The Teardrop Crystal-","title_japanese":"\u8056\u5263\u4f1d\u8aac Legend of Mana -The Teardrop Crystal-","title_synonyms":[],"type":"TV","source":"Game","episodes":null,"status":"Currently Airing","airing":true,"aired":{"from":"2022-10-08T00:00:00+00:00","to":null,"prop":{"from":{"day":8,"month":10,"year":2022},"to":{"day":null,"month":null,"year":null}},"string":"Oct 8, 2022 to ?"},"duration":"23 min","rating":"PG-13 - Teens 13 or older","score":5.95,"scored_by":1535,"rank":9404,"popularity":5252,"members":12651,"favorites":44,"synopsis":"Not far from the town of Domina lives Shiloh, a boy who keeps hearing a voice in his dreams about a mission he must fulfill. But what mission could he be needed for remains unknown. That all changes when he meets two Jumi, a race that\u2019s hunted for their unique gemstones, as a sudden outbreak of attacks against the Jumi occurs. His dream, his quest, becomes clear\u2014help the Jumi and their gemstones! (Source: Crunchyroll)","background":null,"season":"fall","year":2022,"broadcast":{"day":"Saturdays","time":"01:25","timezone":"Asia\/Tokyo","string":"Saturdays at 01:25 (JST)"},"producers":[{"mal_id":58,"type":"anime","name":"Square Enix","url":"https:\/\/myanimelist.net\/anime\/producer\/58\/Square_Enix"},{"mal_id":143,"type":"anime","name":"Mainichi Broadcasting System","url":"https:\/\/myanimelist.net\/anime\/producer\/143\/Mainichi_Broadcasting_System"},{"mal_id":166,"type":"anime","name":"Movic","url":"https:\/\/myanimelist.net\/anime\/producer\/166\/Movic"},{"mal_id":415,"type":"anime","name":"Warner Bros. Japan","url":"https:\/\/myanimelist.net\/anime\/producer\/415\/Warner_Bros_Japan"},{"mal_id":1261,"type":"anime","name":"Good Smile Company","url":"https:\/\/myanimelist.net\/anime\/producer\/1261\/Good_Smile_Company"}],"licensors":[],"studios":[{"mal_id":894,"type":"anime","name":"Graphinica","url":"https:\/\/myanimelist.net\/anime\/producer\/894\/Graphinica"},{"mal_id":1687,"type":"anime","name":"Yokohama Animation Lab","url":"https:\/\/myanimelist.net\/anime\/producer\/1687\/Yokohama_Animation_Lab"}],"genres":[{"mal_id":2,"type":"anime","name":"Adventure","url":"https:\/\/myanimelist.net\/anime\/genre\/2\/Adventure"}],"explicit_genres":[],"themes":[],"demographics":[]},{"mal_id":52381,"url":"https:\/\/myanimelist.net\/anime\/52381\/Aru_Asa_Dummy_Head_Mic_ni_Natteita_Ore-kun_no_Jinsei","images":{"jpg":{"image_url":"https:\/\/cdn.myanimelist.net\/images\/anime\/1135\/125337.jpg","small_image_url":"https:\/\/cdn.myanimelist.net\/images\/anime\/1135\/125337t.jpg","large_image_url":"https:\/\/cdn.myanimelist.net\/images\/anime\/1135\/125337l.jpg"},"webp":{"image_url":"https:\/\/cdn.myanimelist.net\/images\/anime\/1135\/125337.webp","small_image_url":"https:\/\/cdn.myanimelist.net\/images\/anime\/1135\/125337t.webp","large_image_url":"https:\/\/cdn.myanimelist.net\/images\/anime\/1135\/125337l.webp"}},"trailer":{"youtube_id":"X3GjvqjJGJ8","url":"https:\/\/www.youtube.com\/watch?v=X3GjvqjJGJ8","embed_url":"https:\/\/www.youtube.com\/embed\/X3GjvqjJGJ8?enablejsapi=1&wmode=opaque&autoplay=1","images":{"image_url":"https:\/\/img.youtube.com\/vi\/X3GjvqjJGJ8\/default.jpg","small_image_url":"https:\/\/img.youtube.com\/vi\/X3GjvqjJGJ8\/sddefault.jpg","medium_image_url":"https:\/\/img.youtube.com\/vi\/X3GjvqjJGJ8\/mqdefault.jpg","large_image_url":"https:\/\/img.youtube.com\/vi\/X3GjvqjJGJ8\/hqdefault.jpg","maximum_image_url":"https:\/\/img.youtube.com\/vi\/X3GjvqjJGJ8\/maxresdefault.jpg"}},"approved":true,"titles":[{"type":"Default","title":"Aru Asa Dummy Head Mic ni Natteita Ore-kun no Jinsei"},{"type":"Synonym","title":"My Life After I Became a Dummy Head Mic One Morning"},{"type":"Synonym","title":"Aru Asa Dummy Head Mike ni Natteita Ore-kun no Jinsei"},{"type":"Japanese","title":"\u3042\u308b\u671d\u30c0\u30df\u30fc\u30d8\u30c3\u30c9\u30de\u30a4\u30af\u306b\u306a\u3063\u3066\u3044\u305f\u4ffa\u30af\u30f3\u306e\u4eba\u751f"}],"title":"Aru Asa Dummy Head Mic ni Natteita Ore-kun no Jinsei","title_english":null,"title_japanese":"\u3042\u308b\u671d\u30c0\u30df\u30fc\u30d8\u30c3\u30c9\u30de\u30a4\u30af\u306b\u306a\u3063\u3066\u3044\u305f\u4ffa\u30af\u30f3\u306e\u4eba\u751f","title_synonyms":["My Life After I Became a Dummy Head Mic One Morning","Aru Asa Dummy Head Mike ni Natteita Ore-kun no Jinsei"],"type":"TV","source":"Original","episodes":null,"status":"Currently Airing","airing":true,"aired":{"from":"2022-10-13T00:00:00+00:00","to":null,"prop":{"from":{"day":13,"month":10,"year":2022},"to":{"day":null,"month":null,"year":null}},"string":"Oct 13, 2022 to ?"},"duration":"3 min","rating":"PG-13 - Teens 13 or older","score":5.65,"scored_by":985,"rank":10687,"popularity":5430,"members":11505,"favorites":44,"synopsis":"After reincarnating into a dummy head microphone, the protagonist gets involved in the lives of high school girls who do ASMR. The comedic anime will follow these high schoolers as they aim for the ASMR Koshien. (Source: MAL News)","background":null,"season":"fall","year":2022,"broadcast":{"day":"Thursdays","time":"01:00","timezone":"Asia\/Tokyo","string":"Thursdays at 01:00 (JST)"},"producers":[],"licensors":[],"studios":[{"mal_id":1794,"type":"anime","name":"EKACHI EPILKA","url":"https:\/\/myanimelist.net\/anime\/producer\/1794\/EKACHI_EPILKA"},{"mal_id":2248,"type":"anime","name":"Indivision","url":"https:\/\/myanimelist.net\/anime\/producer\/2248\/Indivision"}],"genres":[{"mal_id":26,"type":"anime","name":"Girls Love","url":"https:\/\/myanimelist.net\/anime\/genre\/26\/Girls_Love"},{"mal_id":36,"type":"anime","name":"Slice of Life","url":"https:\/\/myanimelist.net\/anime\/genre\/36\/Slice_of_Life"}],"explicit_genres":[],"themes":[],"demographics":[]},{"mal_id":50638,"url":"https:\/\/myanimelist.net\/anime\/50638\/Muv-Luv_Alternative_2nd_Season","images":{"jpg":{"image_url":"https:\/\/cdn.myanimelist.net\/images\/anime\/1029\/128722.jpg","small_image_url":"https:\/\/cdn.myanimelist.net\/images\/anime\/1029\/128722t.jpg","large_image_url":"https:\/\/cdn.myanimelist.net\/images\/anime\/1029\/128722l.jpg"},"webp":{"image_url":"https:\/\/cdn.myanimelist.net\/images\/anime\/1029\/128722.webp","small_image_url":"https:\/\/cdn.myanimelist.net\/images\/anime\/1029\/128722t.webp","large_image_url":"https:\/\/cdn.myanimelist.net\/images\/anime\/1029\/128722l.webp"}},"trailer":{"youtube_id":"_MdNEjLtmeA","url":"https:\/\/www.youtube.com\/watch?v=_MdNEjLtmeA","embed_url":"https:\/\/www.youtube.com\/embed\/_MdNEjLtmeA?enablejsapi=1&wmode=opaque&autoplay=1","images":{"image_url":"https:\/\/img.youtube.com\/vi\/_MdNEjLtmeA\/default.jpg","small_image_url":"https:\/\/img.youtube.com\/vi\/_MdNEjLtmeA\/sddefault.jpg","medium_image_url":"https:\/\/img.youtube.com\/vi\/_MdNEjLtmeA\/mqdefault.jpg","large_image_url":"https:\/\/img.youtube.com\/vi\/_MdNEjLtmeA\/hqdefault.jpg","maximum_image_url":"https:\/\/img.youtube.com\/vi\/_MdNEjLtmeA\/maxresdefault.jpg"}},"approved":true,"titles":[{"type":"Default","title":"Muv-Luv Alternative 2nd Season"},{"type":"Japanese","title":"\u30de\u30d6\u30e9\u30f4 \u30aa\u30eb\u30bf\u30cd\u30a4\u30c6\u30a3\u30f4"}],"title":"Muv-Luv Alternative 2nd Season","title_english":null,"title_japanese":"\u30de\u30d6\u30e9\u30f4 \u30aa\u30eb\u30bf\u30cd\u30a4\u30c6\u30a3\u30f4","title_synonyms":[],"type":"TV","source":"Visual novel","episodes":12,"status":"Currently Airing","airing":true,"aired":{"from":"2022-10-06T00:00:00+00:00","to":null,"prop":{"from":{"day":6,"month":10,"year":2022},"to":{"day":null,"month":null,"year":null}},"string":"Oct 6, 2022 to ?"},"duration":"22 min per ep","rating":"R+ - Mild Nudity","score":6.66,"scored_by":865,"rank":5550,"popularity":5824,"members":9706,"favorites":38,"synopsis":"A story of the bonds between those who fight, in a world pushed to its limits. On one of the countless parallel worlds that exist throughout spacetime, humanity has fought a decades long war against the BETA, hostile extraterrestrial invaders, using humanoid fighting machines called Tactical Surface Fighters. This is a story of how humanity lives and dies while on the brink of extinction... (Source: Crunchyroll)","background":null,"season":"fall","year":2022,"broadcast":{"day":"Thursdays","time":"00:55","timezone":"Asia\/Tokyo","string":"Thursdays at 00:55 (JST)"},"producers":[{"mal_id":53,"type":"anime","name":"Dentsu","url":"https:\/\/myanimelist.net\/anime\/producer\/53\/Dentsu"},{"mal_id":169,"type":"anime","name":"Fuji TV","url":"https:\/\/myanimelist.net\/anime\/producer\/169\/Fuji_TV"},{"mal_id":843,"type":"anime","name":"BS Fuji","url":"https:\/\/myanimelist.net\/anime\/producer\/843\/BS_Fuji"},{"mal_id":1284,"type":"anime","name":"Avex Pictures","url":"https:\/\/myanimelist.net\/anime\/producer\/1284\/Avex_Pictures"},{"mal_id":1468,"type":"anime","name":"Crunchyroll","url":"https:\/\/myanimelist.net\/anime\/producer\/1468\/Crunchyroll"},{"mal_id":1617,"type":"anime","name":"Tencent Japan","url":"https:\/\/myanimelist.net\/anime\/producer\/1617\/Tencent_Japan"},{"mal_id":2425,"type":"anime","name":"Bandai Namco Music Live","url":"https:\/\/myanimelist.net\/anime\/producer\/2425\/Bandai_Namco_Music_Live"},{"mal_id":2460,"type":"anime","name":"Anchor","url":"https:\/\/myanimelist.net\/anime\/producer\/2460\/Anchor"}],"licensors":[],"studios":[{"mal_id":96,"type":"anime","name":"Yumeta Company","url":"https:\/\/myanimelist.net\/anime\/producer\/96\/Yumeta_Company"},{"mal_id":894,"type":"anime","name":"Graphinica","url":"https:\/\/myanimelist.net\/anime\/producer\/894\/Graphinica"},{"mal_id":2249,"type":"anime","name":"FLAGSHIP LINE","url":"https:\/\/myanimelist.net\/anime\/producer\/2249\/FLAGSHIP_LINE"}],"genres":[{"mal_id":1,"type":"anime","name":"Action","url":"https:\/\/myanimelist.net\/anime\/genre\/1\/Action"},{"mal_id":8,"type":"anime","name":"Drama","url":"https:\/\/myanimelist.net\/anime\/genre\/8\/Drama"},{"mal_id":24,"type":"anime","name":"Sci-Fi","url":"https:\/\/myanimelist.net\/anime\/genre\/24\/Sci-Fi"}],"explicit_genres":[],"themes":[{"mal_id":18,"type":"anime","name":"Mecha","url":"https:\/\/myanimelist.net\/anime\/genre\/18\/Mecha"},{"mal_id":38,"type":"anime","name":"Military","url":"https:\/\/myanimelist.net\/anime\/genre\/38\/Military"}],"demographics":[]},{"mal_id":51293,"url":"https:\/\/myanimelist.net\/anime\/51293\/Eternal_Boys","images":{"jpg":{"image_url":"https:\/\/cdn.myanimelist.net\/images\/anime\/1665\/127107.jpg","small_image_url":"https:\/\/cdn.myanimelist.net\/images\/anime\/1665\/127107t.jpg","large_image_url":"https:\/\/cdn.myanimelist.net\/images\/anime\/1665\/127107l.jpg"},"webp":{"image_url":"https:\/\/cdn.myanimelist.net\/images\/anime\/1665\/127107.webp","small_image_url":"https:\/\/cdn.myanimelist.net\/images\/anime\/1665\/127107t.webp","large_image_url":"https:\/\/cdn.myanimelist.net\/images\/anime\/1665\/127107l.webp"}},"trailer":{"youtube_id":"95gAEoeF-Xs","url":"https:\/\/www.youtube.com\/watch?v=95gAEoeF-Xs","embed_url":"https:\/\/www.youtube.com\/embed\/95gAEoeF-Xs?enablejsapi=1&wmode=opaque&autoplay=1","images":{"image_url":"https:\/\/img.youtube.com\/vi\/95gAEoeF-Xs\/default.jpg","small_image_url":"https:\/\/img.youtube.com\/vi\/95gAEoeF-Xs\/sddefault.jpg","medium_image_url":"https:\/\/img.youtube.com\/vi\/95gAEoeF-Xs\/mqdefault.jpg","large_image_url":"https:\/\/img.youtube.com\/vi\/95gAEoeF-Xs\/hqdefault.jpg","maximum_image_url":"https:\/\/img.youtube.com\/vi\/95gAEoeF-Xs\/maxresdefault.jpg"}},"approved":true,"titles":[{"type":"Default","title":"Eternal Boys"},{"type":"Synonym","title":"Eikyuu Shounen"},{"type":"Japanese","title":"\u6c38\u4e45\u5c11\u5e74 Eternal Boys"},{"type":"English","title":"Eternal Boys"}],"title":"Eternal Boys","title_english":"Eternal Boys","title_japanese":"\u6c38\u4e45\u5c11\u5e74 Eternal Boys","title_synonyms":["Eikyuu Shounen"],"type":"TV","source":"Original","episodes":24,"status":"Currently Airing","airing":true,"aired":{"from":"2022-10-11T00:00:00+00:00","to":null,"prop":{"from":{"day":11,"month":10,"year":2022},"to":{"day":null,"month":null,"year":null}},"string":"Oct 11, 2022 to ?"},"duration":"13 min per ep","rating":"PG-13 - Teens 13 or older","score":6.15,"scored_by":263,"rank":8479,"popularity":6189,"members":8415,"favorites":30,"synopsis":"The story follows six middle-aged men who have experienced success and failures in their lives. One day, they decide to become an idol group and overcome such barriers as their age and their physical condition. (Source: MAL News) The episodes were streamed two weeks in advance of the TV broadcast on Fuji TV's FOD and other streaming services beginning September 26, 2022. Regular broadcasting began on October 11, 2022.","background":null,"season":"fall","year":2022,"broadcast":{"day":"Tuesdays","time":"02:20","timezone":"Asia\/Tokyo","string":"Tuesdays at 02:20 (JST)"},"producers":[],"licensors":[],"studios":[{"mal_id":839,"type":"anime","name":"LIDENFILMS","url":"https:\/\/myanimelist.net\/anime\/producer\/839\/LIDENFILMS"}],"genres":[],"explicit_genres":[],"themes":[{"mal_id":61,"type":"anime","name":"Idols (Male)","url":"https:\/\/myanimelist.net\/anime\/genre\/61\/Idols_Male"},{"mal_id":19,"type":"anime","name":"Music","url":"https:\/\/myanimelist.net\/anime\/genre\/19\/Music"}],"demographics":[]},{"mal_id":46654,"url":"https:\/\/myanimelist.net\/anime\/46654\/IDOLiSH7__Third_Beat_Part_2","images":{"jpg":{"image_url":"https:\/\/cdn.myanimelist.net\/images\/anime\/1458\/125998.jpg","small_image_url":"https:\/\/cdn.myanimelist.net\/images\/anime\/1458\/125998t.jpg","large_image_url":"https:\/\/cdn.myanimelist.net\/images\/anime\/1458\/125998l.jpg"},"webp":{"image_url":"https:\/\/cdn.myanimelist.net\/images\/anime\/1458\/125998.webp","small_image_url":"https:\/\/cdn.myanimelist.net\/images\/anime\/1458\/125998t.webp","large_image_url":"https:\/\/cdn.myanimelist.net\/images\/anime\/1458\/125998l.webp"}},"trailer":{"youtube_id":"Au9jYd7qOH0","url":"https:\/\/www.youtube.com\/watch?v=Au9jYd7qOH0","embed_url":"https:\/\/www.youtube.com\/embed\/Au9jYd7qOH0?enablejsapi=1&wmode=opaque&autoplay=1","images":{"image_url":"https:\/\/img.youtube.com\/vi\/Au9jYd7qOH0\/default.jpg","small_image_url":"https:\/\/img.youtube.com\/vi\/Au9jYd7qOH0\/sddefault.jpg","medium_image_url":"https:\/\/img.youtube.com\/vi\/Au9jYd7qOH0\/mqdefault.jpg","large_image_url":"https:\/\/img.youtube.com\/vi\/Au9jYd7qOH0\/hqdefault.jpg","maximum_image_url":"https:\/\/img.youtube.com\/vi\/Au9jYd7qOH0\/maxresdefault.jpg"}},"approved":true,"titles":[{"type":"Default","title":"IDOLiSH7: Third Beat! Part 2"},{"type":"Japanese","title":"\u30a2\u30a4\u30c9\u30ea\u30c3\u30b7\u30e5\u30bb\u30d6\u30f3"},{"type":"English","title":"IDOLiSH7 Third BEAT! Part 2"}],"title":"IDOLiSH7: Third Beat! Part 2","title_english":"IDOLiSH7 Third BEAT! Part 2","title_japanese":"\u30a2\u30a4\u30c9\u30ea\u30c3\u30b7\u30e5\u30bb\u30d6\u30f3","title_synonyms":[],"type":"TV","source":"Game","episodes":null,"status":"Currently Airing","airing":true,"aired":{"from":"2022-10-02T00:00:00+00:00","to":null,"prop":{"from":{"day":2,"month":10,"year":2022},"to":{"day":null,"month":null,"year":null}},"string":"Oct 2, 2022 to ?"},"duration":"24 min","rating":"PG-13 - Teens 13 or older","score":8.07,"scored_by":614,"rank":491,"popularity":6526,"members":7384,"favorites":80,"synopsis":"IDOLiSH7 is more successful than ever, but no one is smiling because a new threat has taken the stage: the debuting idol group \u0179OO\u013b. Managed by the nefarious entertainment executive Ryou Tsukumo, they will stop at nothing to get their way, resorting to all kinds of underhanded tactics to bring down their rivals. TRIGGER's image has already been ruined by scandal, and IDOLiSH7 and Re:vale are headed for the same fate\u2014or worse. Meanwhile, Zero, the legendary idol who disappeared 15 years ago, continues to haunt the present through those he left behind. His manager seems to be in contact with Tsukumo for his own schemes, and Zero's songwriter reveals himself in a letter after having been missing for years. IDOLiSH7 finds an ally in Re:vale to thwart \u0179OO\u013b's plans while trying to make sense of Zero's colleagues' actions, but it may be impossible for everyone to emerge unscathed. [Written by MAL Rewrite]","background":null,"season":"fall","year":2022,"broadcast":{"day":"Sundays","time":"22:30","timezone":"Asia\/Tokyo","string":"Sundays at 22:30 (JST)"},"producers":[],"licensors":[],"studios":[{"mal_id":1103,"type":"anime","name":"TROYCA","url":"https:\/\/myanimelist.net\/anime\/producer\/1103\/TROYCA"}],"genres":[{"mal_id":8,"type":"anime","name":"Drama","url":"https:\/\/myanimelist.net\/anime\/genre\/8\/Drama"}],"explicit_genres":[],"themes":[{"mal_id":61,"type":"anime","name":"Idols (Male)","url":"https:\/\/myanimelist.net\/anime\/genre\/61\/Idols_Male"},{"mal_id":19,"type":"anime","name":"Music","url":"https:\/\/myanimelist.net\/anime\/genre\/19\/Music"}],"demographics":[]},{"mal_id":50010,"url":"https:\/\/myanimelist.net\/anime\/50010\/Meitantei_Conan__Hannin_no_Hanzawa-san","images":{"jpg":{"image_url":"https:\/\/cdn.myanimelist.net\/images\/anime\/1560\/125527.jpg","small_image_url":"https:\/\/cdn.myanimelist.net\/images\/anime\/1560\/125527t.jpg","large_image_url":"https:\/\/cdn.myanimelist.net\/images\/anime\/1560\/125527l.jpg"},"webp":{"image_url":"https:\/\/cdn.myanimelist.net\/images\/anime\/1560\/125527.webp","small_image_url":"https:\/\/cdn.myanimelist.net\/images\/anime\/1560\/125527t.webp","large_image_url":"https:\/\/cdn.myanimelist.net\/images\/anime\/1560\/125527l.webp"}},"trailer":{"youtube_id":"QSFAnqVGm4o","url":"https:\/\/www.youtube.com\/watch?v=QSFAnqVGm4o","embed_url":"https:\/\/www.youtube.com\/embed\/QSFAnqVGm4o?enablejsapi=1&wmode=opaque&autoplay=1","images":{"image_url":"https:\/\/img.youtube.com\/vi\/QSFAnqVGm4o\/default.jpg","small_image_url":"https:\/\/img.youtube.com\/vi\/QSFAnqVGm4o\/sddefault.jpg","medium_image_url":"https:\/\/img.youtube.com\/vi\/QSFAnqVGm4o\/mqdefault.jpg","large_image_url":"https:\/\/img.youtube.com\/vi\/QSFAnqVGm4o\/hqdefault.jpg","maximum_image_url":"https:\/\/img.youtube.com\/vi\/QSFAnqVGm4o\/maxresdefault.jpg"}},"approved":true,"titles":[{"type":"Default","title":"Meitantei Conan: Hannin no Hanzawa-san"},{"type":"Synonym","title":"Detective Conan: Hannin no Hanzawa-san"},{"type":"Synonym","title":"Detective Conan: Hanzawa the Criminal"},{"type":"Japanese","title":"\u540d\u63a2\u5075\u30b3\u30ca\u30f3 \u72af\u4eba\u306e\u72af\u6ca2\u3055\u3093"},{"type":"English","title":"Detective Conan: The Culprit Hanazawa"}],"title":"Meitantei Conan: Hannin no Hanzawa-san","title_english":"Detective Conan: The Culprit Hanazawa","title_japanese":"\u540d\u63a2\u5075\u30b3\u30ca\u30f3 \u72af\u4eba\u306e\u72af\u6ca2\u3055\u3093","title_synonyms":["Detective Conan: Hannin no Hanzawa-san","Detective Conan: Hanzawa the Criminal"],"type":"TV","source":"Manga","episodes":null,"status":"Currently Airing","airing":true,"aired":{"from":"2022-10-04T00:00:00+00:00","to":null,"prop":{"from":{"day":4,"month":10,"year":2022},"to":{"day":null,"month":null,"year":null}},"string":"Oct 4, 2022 to ?"},"duration":"9 min","rating":"PG-13 - Teens 13 or older","score":6.79,"scored_by":514,"rank":4930,"popularity":7637,"members":5014,"favorites":15,"synopsis":"Anime adaptation of the spin-off manga Meitantei Conan: Hannin no Hanzawa-san that stars the black-silhouetted \"criminal\" that appears in Detective Conan representing the mystery culprits.","background":null,"season":"fall","year":2022,"broadcast":{"day":"Tuesdays","time":"01:05","timezone":"Asia\/Tokyo","string":"Tuesdays at 01:05 (JST)"},"producers":[{"mal_id":62,"type":"anime","name":"Shogakukan-Shueisha Productions","url":"https:\/\/myanimelist.net\/anime\/producer\/62\/Shogakukan-Shueisha_Productions"}],"licensors":[],"studios":[{"mal_id":73,"type":"anime","name":"TMS Entertainment","url":"https:\/\/myanimelist.net\/anime\/producer\/73\/TMS_Entertainment"}],"genres":[{"mal_id":4,"type":"anime","name":"Comedy","url":"https:\/\/myanimelist.net\/anime\/genre\/4\/Comedy"},{"mal_id":7,"type":"anime","name":"Mystery","url":"https:\/\/myanimelist.net\/anime\/genre\/7\/Mystery"}],"explicit_genres":[],"themes":[],"demographics":[{"mal_id":27,"type":"anime","name":"Shounen","url":"https:\/\/myanimelist.net\/anime\/genre\/27\/Shounen"}]},{"mal_id":53012,"url":"https:\/\/myanimelist.net\/anime\/53012\/Human_Bug_Daigaku","images":{"jpg":{"image_url":"https:\/\/cdn.myanimelist.net\/images\/anime\/1265\/128725.jpg","small_image_url":"https:\/\/cdn.myanimelist.net\/images\/anime\/1265\/128725t.jpg","large_image_url":"https:\/\/cdn.myanimelist.net\/images\/anime\/1265\/128725l.jpg"},"webp":{"image_url":"https:\/\/cdn.myanimelist.net\/images\/anime\/1265\/128725.webp","small_image_url":"https:\/\/cdn.myanimelist.net\/images\/anime\/1265\/128725t.webp","large_image_url":"https:\/\/cdn.myanimelist.net\/images\/anime\/1265\/128725l.webp"}},"trailer":{"youtube_id":"JY6UlQIGF6Q","url":"https:\/\/www.youtube.com\/watch?v=JY6UlQIGF6Q","embed_url":"https:\/\/www.youtube.com\/embed\/JY6UlQIGF6Q?enablejsapi=1&wmode=opaque&autoplay=1","images":{"image_url":"https:\/\/img.youtube.com\/vi\/JY6UlQIGF6Q\/default.jpg","small_image_url":"https:\/\/img.youtube.com\/vi\/JY6UlQIGF6Q\/sddefault.jpg","medium_image_url":"https:\/\/img.youtube.com\/vi\/JY6UlQIGF6Q\/mqdefault.jpg","large_image_url":"https:\/\/img.youtube.com\/vi\/JY6UlQIGF6Q\/hqdefault.jpg","maximum_image_url":"https:\/\/img.youtube.com\/vi\/JY6UlQIGF6Q\/maxresdefault.jpg"}},"approved":true,"titles":[{"type":"Default","title":"Human Bug Daigaku"},{"type":"Japanese","title":"\u30d2\u30e5\u30fc\u30de\u30f3\u30d0\u30b0\u5927\u5b66"},{"type":"English","title":"The Human Crazy University"}],"title":"Human Bug Daigaku","title_english":"The Human Crazy University","title_japanese":"\u30d2\u30e5\u30fc\u30de\u30f3\u30d0\u30b0\u5927\u5b66","title_synonyms":[],"type":"TV","source":"Web manga","episodes":null,"status":"Currently Airing","airing":true,"aired":{"from":"2022-10-05T00:00:00+00:00","to":null,"prop":{"from":{"day":5,"month":10,"year":2022},"to":{"day":null,"month":null,"year":null}},"string":"Oct 5, 2022 to ?"},"duration":"23 min","rating":"PG-13 - Teens 13 or older","score":5.72,"scored_by":870,"rank":10417,"popularity":7950,"members":4498,"favorites":10,"synopsis":"Satake Hirofumi is a prisoner on death row for murdering his fianc\u00e9e. He's also an \"Undeadman\" who has survived many desperate situations. For this, he has earned the interest of a research institution called \"Human Crazy University,\" which studies real-life miraculous phenomena and the people who become entangled in them. Now a subject of their research, Satake relates to them his memories of his immortal, yet unhappy, life. Why did he kill his fianc\u00e9e? Soon enough, the truth sheds light on a much bigger conspiracy... (Source: Crunchyroll)","background":null,"season":"fall","year":2022,"broadcast":{"day":"Wednesdays","time":"22:00","timezone":"Asia\/Tokyo","string":"Wednesdays at 22:00 (JST)"},"producers":[{"mal_id":323,"type":"anime","name":"Nippon Columbia","url":"https:\/\/myanimelist.net\/anime\/producer\/323\/Nippon_Columbia"},{"mal_id":1468,"type":"anime","name":"Crunchyroll","url":"https:\/\/myanimelist.net\/anime\/producer\/1468\/Crunchyroll"},{"mal_id":1492,"type":"anime","name":"Yomiuri TV Enterprise","url":"https:\/\/myanimelist.net\/anime\/producer\/1492\/Yomiuri_TV_Enterprise"},{"mal_id":1996,"type":"anime","name":"MAGNET","url":"https:\/\/myanimelist.net\/anime\/producer\/1996\/MAGNET"},{"mal_id":2610,"type":"anime","name":"K contents","url":"https:\/\/myanimelist.net\/anime\/producer\/2610\/K_contents"}],"licensors":[],"studios":[{"mal_id":276,"type":"anime","name":"DLE","url":"https:\/\/myanimelist.net\/anime\/producer\/276\/DLE"}],"genres":[{"mal_id":4,"type":"anime","name":"Comedy","url":"https:\/\/myanimelist.net\/anime\/genre\/4\/Comedy"}],"explicit_genres":[],"themes":[],"demographics":[]},{"mal_id":43771,"url":"https:\/\/myanimelist.net\/anime\/43771\/Vazzrock_The_Animation","images":{"jpg":{"image_url":"https:\/\/cdn.myanimelist.net\/images\/anime\/1488\/127334.jpg","small_image_url":"https:\/\/cdn.myanimelist.net\/images\/anime\/1488\/127334t.jpg","large_image_url":"https:\/\/cdn.myanimelist.net\/images\/anime\/1488\/127334l.jpg"},"webp":{"image_url":"https:\/\/cdn.myanimelist.net\/images\/anime\/1488\/127334.webp","small_image_url":"https:\/\/cdn.myanimelist.net\/images\/anime\/1488\/127334t.webp","large_image_url":"https:\/\/cdn.myanimelist.net\/images\/anime\/1488\/127334l.webp"}},"trailer":{"youtube_id":"OcN0l1qDsHk","url":"https:\/\/www.youtube.com\/watch?v=OcN0l1qDsHk","embed_url":"https:\/\/www.youtube.com\/embed\/OcN0l1qDsHk?enablejsapi=1&wmode=opaque&autoplay=1","images":{"image_url":"https:\/\/img.youtube.com\/vi\/OcN0l1qDsHk\/default.jpg","small_image_url":"https:\/\/img.youtube.com\/vi\/OcN0l1qDsHk\/sddefault.jpg","medium_image_url":"https:\/\/img.youtube.com\/vi\/OcN0l1qDsHk\/mqdefault.jpg","large_image_url":"https:\/\/img.youtube.com\/vi\/OcN0l1qDsHk\/hqdefault.jpg","maximum_image_url":"https:\/\/img.youtube.com\/vi\/OcN0l1qDsHk\/maxresdefault.jpg"}},"approved":true,"titles":[{"type":"Default","title":"Vazzrock The Animation"},{"type":"Japanese","title":"VAZZROCK THE ANIMATION"},{"type":"English","title":"Vazzrock the Animation"}],"title":"Vazzrock The Animation","title_english":"Vazzrock the Animation","title_japanese":"VAZZROCK THE ANIMATION","title_synonyms":[],"type":"TV","source":"Music","episodes":13,"status":"Currently Airing","airing":true,"aired":{"from":"2022-10-05T00:00:00+00:00","to":null,"prop":{"from":{"day":5,"month":10,"year":2022},"to":{"day":null,"month":null,"year":null}},"string":"Oct 5, 2022 to ?"},"duration":"23 min per ep","rating":"PG-13 - Teens 13 or older","score":4.99,"scored_by":412,"rank":12566,"popularity":8072,"members":4350,"favorites":22,"synopsis":"VAZZY and ROCK DOWN are the two units that make up Tsukino Talent Production's all-male VAZZROCK group. Led by Takaaki Mamiya and Shou Onoda respectively, both units announce via a round-table livestream that they are working hard to prepare for the upcoming VAZZROCK Live Flawless event. From taking extra dancing and singing lessons to starring in a TV period drama, these 12 idols must give it their all as they work toward a spectacular show that will impress their fans. [Written by MAL Rewrite]","background":"AbemaTV streamed each episode one day in advance of the TV broadcast starting on October 4, 2022. Regular TV broadcasting began on October 5, 2022. Vazzrock The Animation was released on Blu-ray in seven volumes by Movic from January 27, 2023 to July 28, 2023.","season":"fall","year":2022,"broadcast":{"day":"Wednesdays","time":"22:30","timezone":"Asia\/Tokyo","string":"Wednesdays at 22:30 (JST)"},"producers":[],"licensors":[],"studios":[{"mal_id":753,"type":"anime","name":"PRA","url":"https:\/\/myanimelist.net\/anime\/producer\/753\/PRA"}],"genres":[],"explicit_genres":[],"themes":[{"mal_id":61,"type":"anime","name":"Idols (Male)","url":"https:\/\/myanimelist.net\/anime\/genre\/61\/Idols_Male"},{"mal_id":19,"type":"anime","name":"Music","url":"https:\/\/myanimelist.net\/anime\/genre\/19\/Music"}],"demographics":[]},{"mal_id":51986,"url":"https:\/\/myanimelist.net\/anime\/51986\/Pui_Pui_Molcar__Driving_School","images":{"jpg":{"image_url":"https:\/\/cdn.myanimelist.net\/images\/anime\/1382\/125361.jpg","small_image_url":"https:\/\/cdn.myanimelist.net\/images\/anime\/1382\/125361t.jpg","large_image_url":"https:\/\/cdn.myanimelist.net\/images\/anime\/1382\/125361l.jpg"},"webp":{"image_url":"https:\/\/cdn.myanimelist.net\/images\/anime\/1382\/125361.webp","small_image_url":"https:\/\/cdn.myanimelist.net\/images\/anime\/1382\/125361t.webp","large_image_url":"https:\/\/cdn.myanimelist.net\/images\/anime\/1382\/125361l.webp"}},"trailer":{"youtube_id":"RcouHCSRjA4","url":"https:\/\/www.youtube.com\/watch?v=RcouHCSRjA4","embed_url":"https:\/\/www.youtube.com\/embed\/RcouHCSRjA4?enablejsapi=1&wmode=opaque&autoplay=1","images":{"image_url":"https:\/\/img.youtube.com\/vi\/RcouHCSRjA4\/default.jpg","small_image_url":"https:\/\/img.youtube.com\/vi\/RcouHCSRjA4\/sddefault.jpg","medium_image_url":"https:\/\/img.youtube.com\/vi\/RcouHCSRjA4\/mqdefault.jpg","large_image_url":"https:\/\/img.youtube.com\/vi\/RcouHCSRjA4\/hqdefault.jpg","maximum_image_url":"https:\/\/img.youtube.com\/vi\/RcouHCSRjA4\/maxresdefault.jpg"}},"approved":true,"titles":[{"type":"Default","title":"Pui Pui Molcar: Driving School"},{"type":"Japanese","title":"PUI PUI \u30e2\u30eb\u30ab\u30fc DRIVING SCHOOL"}],"title":"Pui Pui Molcar: Driving School","title_english":null,"title_japanese":"PUI PUI \u30e2\u30eb\u30ab\u30fc DRIVING SCHOOL","title_synonyms":[],"type":"TV","source":"Original","episodes":12,"status":"Currently Airing","airing":true,"aired":{"from":"2022-10-08T00:00:00+00:00","to":null,"prop":{"from":{"day":8,"month":10,"year":2022},"to":{"day":null,"month":null,"year":null}},"string":"Oct 8, 2022 to ?"},"duration":"2 min per ep","rating":"G - All Ages","score":7.01,"scored_by":331,"rank":3918,"popularity":8777,"members":3289,"favorites":15,"synopsis":"New series for Pui Pui Molcar.","background":null,"season":"fall","year":2022,"broadcast":{"day":"Saturdays","time":"07:00","timezone":"Asia\/Tokyo","string":"Saturdays at 07:00 (JST)"},"producers":[],"licensors":[],"studios":[{"mal_id":247,"type":"anime","name":"Shin-Ei Animation","url":"https:\/\/myanimelist.net\/anime\/producer\/247\/Shin-Ei_Animation"}],"genres":[{"mal_id":4,"type":"anime","name":"Comedy","url":"https:\/\/myanimelist.net\/anime\/genre\/4\/Comedy"}],"explicit_genres":[],"themes":[{"mal_id":51,"type":"anime","name":"Anthropomorphic","url":"https:\/\/myanimelist.net\/anime\/genre\/51\/Anthropomorphic"}],"demographics":[{"mal_id":15,"type":"anime","name":"Kids","url":"https:\/\/myanimelist.net\/anime\/genre\/15\/Kids"}]},{"mal_id":49179,"url":"https:\/\/myanimelist.net\/anime\/49179\/Reiwa_no_Di_Gi_Charat","images":{"jpg":{"image_url":"https:\/\/cdn.myanimelist.net\/images\/anime\/1343\/124987.jpg","small_image_url":"https:\/\/cdn.myanimelist.net\/images\/anime\/1343\/124987t.jpg","large_image_url":"https:\/\/cdn.myanimelist.net\/images\/anime\/1343\/124987l.jpg"},"webp":{"image_url":"https:\/\/cdn.myanimelist.net\/images\/anime\/1343\/124987.webp","small_image_url":"https:\/\/cdn.myanimelist.net\/images\/anime\/1343\/124987t.webp","large_image_url":"https:\/\/cdn.myanimelist.net\/images\/anime\/1343\/124987l.webp"}},"trailer":{"youtube_id":"b6pIDLFJEOA","url":"https:\/\/www.youtube.com\/watch?v=b6pIDLFJEOA","embed_url":"https:\/\/www.youtube.com\/embed\/b6pIDLFJEOA?enablejsapi=1&wmode=opaque&autoplay=1","images":{"image_url":"https:\/\/img.youtube.com\/vi\/b6pIDLFJEOA\/default.jpg","small_image_url":"https:\/\/img.youtube.com\/vi\/b6pIDLFJEOA\/sddefault.jpg","medium_image_url":"https:\/\/img.youtube.com\/vi\/b6pIDLFJEOA\/mqdefault.jpg","large_image_url":"https:\/\/img.youtube.com\/vi\/b6pIDLFJEOA\/hqdefault.jpg","maximum_image_url":"https:\/\/img.youtube.com\/vi\/b6pIDLFJEOA\/maxresdefault.jpg"}},"approved":true,"titles":[{"type":"Default","title":"Reiwa no Di Gi Charat"},{"type":"Japanese","title":"\u4ee4\u548c\u306e\u30c7\u30fb\u30b8\u30fb\u30ad\u30e3\u30e9\u30c3\u30c8"}],"title":"Reiwa no Di Gi Charat","title_english":null,"title_japanese":"\u4ee4\u548c\u306e\u30c7\u30fb\u30b8\u30fb\u30ad\u30e3\u30e9\u30c3\u30c8","title_synonyms":[],"type":"TV","source":"Manga","episodes":null,"status":"Currently Airing","airing":true,"aired":{"from":"2022-10-07T00:00:00+00:00","to":null,"prop":{"from":{"day":7,"month":10,"year":2022},"to":{"day":null,"month":null,"year":null}},"string":"Oct 7, 2022 to ?"},"duration":"4 min","rating":null,"score":5.97,"scored_by":232,"rank":9313,"popularity":9019,"members":3034,"favorites":9,"synopsis":"New mini anime series for Di Gi Charat, part of the celebration for the franchise's 24th anniversary next year.","background":null,"season":"fall","year":2022,"broadcast":{"day":"Fridays","time":"23:00","timezone":"Asia\/Tokyo","string":"Fridays at 23:00 (JST)"},"producers":[],"licensors":[],"studios":[{"mal_id":839,"type":"anime","name":"LIDENFILMS","url":"https:\/\/myanimelist.net\/anime\/producer\/839\/LIDENFILMS"}],"genres":[{"mal_id":4,"type":"anime","name":"Comedy","url":"https:\/\/myanimelist.net\/anime\/genre\/4\/Comedy"}],"explicit_genres":[],"themes":[],"demographics":[]},{"mal_id":50559,"url":"https:\/\/myanimelist.net\/anime\/50559\/Megaton-kyuu_Musashi_2nd_Season","images":{"jpg":{"image_url":"https:\/\/cdn.myanimelist.net\/images\/anime\/1207\/127832.jpg","small_image_url":"https:\/\/cdn.myanimelist.net\/images\/anime\/1207\/127832t.jpg","large_image_url":"https:\/\/cdn.myanimelist.net\/images\/anime\/1207\/127832l.jpg"},"webp":{"image_url":"https:\/\/cdn.myanimelist.net\/images\/anime\/1207\/127832.webp","small_image_url":"https:\/\/cdn.myanimelist.net\/images\/anime\/1207\/127832t.webp","large_image_url":"https:\/\/cdn.myanimelist.net\/images\/anime\/1207\/127832l.webp"}},"trailer":{"youtube_id":"LYS1AHH-xrg","url":"https:\/\/www.youtube.com\/watch?v=LYS1AHH-xrg","embed_url":"https:\/\/www.youtube.com\/embed\/LYS1AHH-xrg?enablejsapi=1&wmode=opaque&autoplay=1","images":{"image_url":"https:\/\/img.youtube.com\/vi\/LYS1AHH-xrg\/default.jpg","small_image_url":"https:\/\/img.youtube.com\/vi\/LYS1AHH-xrg\/sddefault.jpg","medium_image_url":"https:\/\/img.youtube.com\/vi\/LYS1AHH-xrg\/mqdefault.jpg","large_image_url":"https:\/\/img.youtube.com\/vi\/LYS1AHH-xrg\/hqdefault.jpg","maximum_image_url":"https:\/\/img.youtube.com\/vi\/LYS1AHH-xrg\/maxresdefault.jpg"}},"approved":true,"titles":[{"type":"Default","title":"Megaton-kyuu Musashi 2nd Season"},{"type":"Synonym","title":"Megaton Musashi"},{"type":"Japanese","title":"\u30e1\u30ac\u30c8\u30f3\u7d1a\u30e0\u30b5\u30b7"}],"title":"Megaton-kyuu Musashi 2nd Season","title_english":null,"title_japanese":"\u30e1\u30ac\u30c8\u30f3\u7d1a\u30e0\u30b5\u30b7","title_synonyms":["Megaton Musashi"],"type":"TV","source":"Mixed media","episodes":null,"status":"Currently Airing","airing":true,"aired":{"from":"2022-10-07T00:00:00+00:00","to":null,"prop":{"from":{"day":7,"month":10,"year":2022},"to":{"day":null,"month":null,"year":null}},"string":"Oct 7, 2022 to ?"},"duration":"25 min","rating":"PG-13 - Teens 13 or older","score":6.29,"scored_by":209,"rank":7615,"popularity":9630,"members":2435,"favorites":4,"synopsis":"Second season of Megaton-kyuu Musashi.","background":null,"season":"fall","year":2022,"broadcast":{"day":"Fridays","time":"22:00","timezone":"Asia\/Tokyo","string":"Fridays at 22:00 (JST)"},"producers":[],"licensors":[],"studios":[{"mal_id":28,"type":"anime","name":"OLM","url":"https:\/\/myanimelist.net\/anime\/producer\/28\/OLM"}],"genres":[{"mal_id":1,"type":"anime","name":"Action","url":"https:\/\/myanimelist.net\/anime\/genre\/1\/Action"},{"mal_id":24,"type":"anime","name":"Sci-Fi","url":"https:\/\/myanimelist.net\/anime\/genre\/24\/Sci-Fi"}],"explicit_genres":[],"themes":[{"mal_id":18,"type":"anime","name":"Mecha","url":"https:\/\/myanimelist.net\/anime\/genre\/18\/Mecha"},{"mal_id":23,"type":"anime","name":"School","url":"https:\/\/myanimelist.net\/anime\/genre\/23\/School"}],"demographics":[]},{"mal_id":53011,"url":"https:\/\/myanimelist.net\/anime\/53011\/Mamekichi_Mameko_NEET_no_Nichijou","images":{"jpg":{"image_url":"https:\/\/cdn.myanimelist.net\/images\/anime\/1920\/127864.jpg","small_image_url":"https:\/\/cdn.myanimelist.net\/images\/anime\/1920\/127864t.jpg","large_image_url":"https:\/\/cdn.myanimelist.net\/images\/anime\/1920\/127864l.jpg"},"webp":{"image_url":"https:\/\/cdn.myanimelist.net\/images\/anime\/1920\/127864.webp","small_image_url":"https:\/\/cdn.myanimelist.net\/images\/anime\/1920\/127864t.webp","large_image_url":"https:\/\/cdn.myanimelist.net\/images\/anime\/1920\/127864l.webp"}},"trailer":{"youtube_id":"vAiZVrSfaUM","url":"https:\/\/www.youtube.com\/watch?v=vAiZVrSfaUM","embed_url":"https:\/\/www.youtube.com\/embed\/vAiZVrSfaUM?enablejsapi=1&wmode=opaque&autoplay=1","images":{"image_url":"https:\/\/img.youtube.com\/vi\/vAiZVrSfaUM\/default.jpg","small_image_url":"https:\/\/img.youtube.com\/vi\/vAiZVrSfaUM\/sddefault.jpg","medium_image_url":"https:\/\/img.youtube.com\/vi\/vAiZVrSfaUM\/mqdefault.jpg","large_image_url":"https:\/\/img.youtube.com\/vi\/vAiZVrSfaUM\/hqdefault.jpg","maximum_image_url":"https:\/\/img.youtube.com\/vi\/vAiZVrSfaUM\/maxresdefault.jpg"}},"approved":true,"titles":[{"type":"Default","title":"Mamekichi Mameko NEET no Nichijou"},{"type":"Japanese","title":"\u307e\u3081\u304d\u3061\u307e\u3081\u3053\u30cb\u30fc\u30c8\u306e\u65e5\u5e38"}],"title":"Mamekichi Mameko NEET no Nichijou","title_english":null,"title_japanese":"\u307e\u3081\u304d\u3061\u307e\u3081\u3053\u30cb\u30fc\u30c8\u306e\u65e5\u5e38","title_synonyms":[],"type":"TV","source":"Web manga","episodes":48,"status":"Currently Airing","airing":true,"aired":{"from":"2022-10-03T00:00:00+00:00","to":null,"prop":{"from":{"day":3,"month":10,"year":2022},"to":{"day":null,"month":null,"year":null}},"string":"Oct 3, 2022 to ?"},"duration":"1 min per ep","rating":"PG-13 - Teens 13 or older","score":null,"scored_by":null,"rank":13578,"popularity":14144,"members":493,"favorites":2,"synopsis":"Mameko is a NEET (Not in Education, Employment, or Training). She lives with her dog Komachi and her cats Tabi, Simba, and Melo. Mameko promises God that she will do her best from tomorrow, but the next day she says, \"God is telling me to sleep...\" and loses to herself. This is the story of Mameko's everyday life, which seems to be nothing and is somewhat strange. (Source: Official Site)","background":null,"season":"fall","year":2022,"broadcast":{"day":null,"time":null,"timezone":null,"string":"Unknown"},"producers":[],"licensors":[],"studios":[{"mal_id":200,"type":"anime","name":"Tezuka Productions","url":"https:\/\/myanimelist.net\/anime\/producer\/200\/Tezuka_Productions"}],"genres":[{"mal_id":4,"type":"anime","name":"Comedy","url":"https:\/\/myanimelist.net\/anime\/genre\/4\/Comedy"}],"explicit_genres":[],"themes":[],"demographics":[]}]}